Workbook

Sheet Space technology manufacturers
A1: Company | B1: Country | C1: Revenue 2021 (in milion $) | D1: Revenue 2022 (in milion $) | E1: #Shareholders | F1: Share of non-EU direct ownership | G1: Share of non-EU indirect ownership | H1: Weighted share of non-EU direct industry ownership | I1: Weighted share of non-EU indirect industry ownership | J1: US direct ownership | K1: US indirect ownership | L1: Canada direct ownership | M1: Canada indirect ownership | N1: UK direct ownership | O1: UK indirect ownership | P1: Switzerland direct ownership | Q1: Switzerland direct ownership | R1: Norway direct ownership | S1: Norway indirect ownership | T1: US direct share | U1: US indirect share | V1: Canada direct share | W1: Canada indirect share | X1: UK direct share | Y1: UK indirect share | Z1: Switzerland direct share | AA1: Switzerland indirect share | AB1: Norway direct share | AC1: Norway indirect share | AD1: Owned by | AE1: Country owner | AF1: Revenu owner 2021 (in milion $) | AG1: #Shareholders owner
A2: Aerospacelab | B2: BE | E2: 7
A3: Air Liquide Advanced Technologies | B3: FR | C3: 306.2 | E3: 2 | F3: =Ownership!D235/Ownership!D236 -> 0.052329824 | G3: =Ownership!E235/Ownership!E236 -> 0.73739148 | H3: =F3*C3 -> 16.023392 | I3: =G3*C3 -> 225.78927 | J3: =(Ownership!D184)/Ownership!D236 -> 0.052329824 | K3: =Ownership!E230/Ownership!E236 -> 0.49179961 | L3: =Ownership!D231/Ownership!D236 -> 0 | M3: =Ownership!E231/Ownership!E236 -> 0.062247944 | N3: =Ownership!D232/Ownership!D236 -> 0 | O3: =Ownership!E232/Ownership!E236 -> 0.017507234 | P3: =Ownership!D233/Ownership!D236 -> 0 | Q3: =Ownership!E233/Ownership!E236 -> 0.031123972 | R3: =Ownership!D234/Ownership!D236 -> 0 | S3: =Ownership!E234/Ownership!E236 -> 0.094020333 | T3: =J3*C3 -> 16.023392 | U3: =K3*C3 -> 150.58904 | V3: =L3*C3 -> 0 | W3: =M3*C3 -> 19.060321 | X3: =N3*C3 -> 0 | Y3: =O3*C3 -> 5.3607152 | Z3: =P3*C3 -> 0 | AA3: =Q3*C3 -> 9.5301603 | AB3: =R3*C3 -> 0 | AC3: =S3*C3 -> 28.789026 | AD3: L'AIR LIQUIDE SOCIETE ANONYME POUR L'ETUDE ET L'EXPLOITATION DES PROCEDES GEORGES CLAUDE | AE3: FR | AF3: 32468 | AG3: 49
A4: Air Liquide France Industry | B4: FR | D4: 1773.2 | E4: 2 | F4: =Ownership!D235/Ownership!D236 -> 0.052329824 | G4: =Ownership!E235/Ownership!E236 -> 0.73739148 | H4: =F4*D4 -> 92.791244 | I4: =G4*D4 -> 1307.5426 | J4: =(Ownership!D184)/Ownership!D236 -> 0.052329824 | K4: =Ownership!E230/Ownership!E236 -> 0.49179961 | L4: =Ownership!D231/Ownership!D236 -> 0 | M4: =Ownership!E231/Ownership!E236 -> 0.062247944 | N4: =Ownership!D232/Ownership!D236 -> 0 | O4: =Ownership!E232/Ownership!E236 -> 0.017507234 | P4: =Ownership!D233/Ownership!D236 -> 0 | Q4: =Ownership!E233/Ownership!E236 -> 0.031123972 | R4: =Ownership!D234/Ownership!D236 -> 0 | S4: =Ownership!E234/Ownership!E236 -> 0.094020333 | T4: =J4*D4 -> 92.791244 | U4: =K4*D4 -> 872.05907 | V4: =L4*D4 -> 0 | W4: =M4*D4 -> 110.37806 | X4: =N4*D4 -> 0 | Y4: =O4*D4 -> 31.043828 | Z4: =P4*D4 -> 0 | AA4: =Q4*D4 -> 55.189028 | AB4: =R4*D4 -> 0 | AC4: =S4*D4 -> 166.71685 | AD4: L'AIR LIQUIDE SOCIETE ANONYME POUR L'ETUDE ET L'EXPLOITATION DES PROCEDES GEORGES CLAUDE | AE4: FR | AF4: 32468 | AG4: 49
A5: Airbus Defence & Space GMBH | B5: DE | C5: 4645.9 | E5: 2 | F5: =Ownership!D110/Ownership!D111 -> 0 | G5: =Ownership!E84/Ownership!E85 -> 0.13841121 | H5: =F5*C5 -> 0 | I5: =G5*C5 -> 643.04466 | J5: =Ownership!D79/Ownership!D85 -> 0.092754528 | K5: =Ownership!E79/Ownership!E85 -> 0.13841121 | L5: =Ownership!D80/Ownership!D85 -> 0 | M5: =Ownership!E80/Ownership!E85 -> 0 | N5: =Ownership!D81/Ownership!D85 -> 0 | O5: =Ownership!E81/Ownership!E85 -> 0 | P5: =Ownership!D82/Ownership!D85 -> 0 | Q5: =Ownership!E82/Ownership!E85 -> 0 | R5: =Ownership!D83/Ownership!D85 -> 0 | S5: =Ownership!E83/Ownership!E85 -> 0 | T5: =J5*C5 -> 430.92826 | U5: =K5*C5 -> 643.04466 | V5: =L5*C5 -> 0 | W5: =M5*C5 -> 0 | X5: =N5*C5 -> 0 | Y5: =O5*C5 -> 0 | Z5: =P5*C5 -> 0 | AA5: =Q5*C5 -> 0 | AB5: =R5*C5 -> 0 | AC5: =S5*C5 -> 0 | AD5: Airbus SE | AE5: NL | AF5: 63179 | AG5: 12
A6: Airbus Defence & Space Netherlands BV | B6: NL | C6: 62.3 | E6: 1 | F6: =Ownership!D110/Ownership!D111 -> 0 | G6: =Ownership!E84/Ownership!E85 -> 0.13841121 | H6: =F6*C6 -> 0 | I6: =G6*C6 -> 8.6230186 | J6: =Ownership!D79/Ownership!D85 -> 0.092754528 | K6: =Ownership!E79/Ownership!E85 -> 0.13841121 | L6: =Ownership!D80/Ownership!D85 -> 0 | M6: =Ownership!E80/Ownership!E85 -> 0 | N6: =Ownership!D81/Ownership!D85 -> 0 | O6: =Ownership!E81/Ownership!E85 -> 0 | P6: =Ownership!E81/Ownership!E85 -> 0 | Q6: =Ownership!E81/Ownership!E85 -> 0 | R6: =Ownership!E81/Ownership!E85 -> 0 | S6: =Ownership!E81/Ownership!E85 -> 0 | T6: =J6*C6 -> 5.7786071 | U6: =K6*C6 -> 8.6230186 | V6: =L6*C6 -> 0 | W6: =M6*C6 -> 0 | X6: =N6*C6 -> 0 | Y6: =O6*C6 -> 0 | Z6: =P6*C6 -> 0 | AA6: =Q6*C6 -> 0 | AB6: =R6*C6 -> 0 | AC6: =S6*C6 -> 0 | AD6: Airbus SE | AE6: NL | AF6: 63179 | AG6: 12
A7: Airbus Defence & Space SA | B7: ES | C7: 3769.6 | E7: 1 | F7: =Ownership!D110/Ownership!D111 -> 0 | G7: =Ownership!E84/Ownership!E85 -> 0.13841121 | H7: =F7*C7 -> 0 | I7: =G7*C7 -> 521.75491 | J7: =Ownership!D79/Ownership!D85 -> 0.092754528 | K7: =Ownership!E79/Ownership!E85 -> 0.13841121 | L7: =Ownership!D80/Ownership!D85 -> 0 | M7: =Ownership!E80/Ownership!E85 -> 0 | N7: =Ownership!D81/Ownership!D85 -> 0 | O7: =Ownership!E81/Ownership!E85 -> 0 | P7: =Ownership!E81/Ownership!E85 -> 0 | Q7: =Ownership!E81/Ownership!E85 -> 0 | R7: =Ownership!E81/Ownership!E85 -> 0 | S7: =Ownership!E81/Ownership!E85 -> 0 | T7: =J7*$C$7 -> 349.64747 | U7: =K7*$C$7 -> 521.75491 | V7: =L7*$C$7 -> 0 | W7: =M7*$C$7 -> 0 | X7: =N7*$C$7 -> 0 | Y7: =O7*$C$7 -> 0 | Z7: =P7*$C$7 -> 0 | AA7: =Q7*$C$7 -> 0 | ... AC7: =S7*$C$7 -> 0 | AD7: Airbus SE | AE7: NL | AF7: 63179 | AG7: 12
A8: Airbus Defence & Space SAS | B8: FR | C8: 3335.7 | E8: 1 | F8: =Ownership!D110/Ownership!D111 -> 0 | G8: =Ownership!E84/Ownership!E85 -> 0.13841121 | H8: =F8*C8 -> 0 | I8: =G8*C8 -> 461.69828 | J8: =Ownership!D79/Ownership!D85 -> 0.092754528 | K8: =Ownership!E79/Ownership!E85 -> 0.13841121 | L8: =Ownership!D80/Ownership!D85 -> 0 | M8: =Ownership!E80/Ownership!E85 -> 0 | N8: =Ownership!D81/Ownership!D85 -> 0 | O8: =Ownership!E81/Ownership!E85 -> 0 | P8: =Ownership!E81/Ownership!E85 -> 0 | Q8: =Ownership!E81/Ownership!E85 -> 0 | R8: =Ownership!E81/Ownership!E85 -> 0 | S8: =Ownership!E81/Ownership!E85 -> 0 | T8: =J8*$C$8 -> 309.40128 | U8: =K8*$C$8 -> 461.69828 | V8: =L8*$C$8 -> 0 | W8: =M8*$C$8 -> 0 | X8: =N8*$C$8 -> 0 | Y8: =O8*$C$8 -> 0 | Z8: =P8*$C$8 -> 0 | AA8: =Q8*$C$8 -> 0 | ... AC8: =S8*$C$8 -> 0 | AD8: Airbus SE | AE8: NL | AF8: 63179 | AG8: 12
A9: ALTEC (Aerospace Logistics Technology Engineering Company) | B9: IT | D9: 23.8 | E9: 3 | F9: =Ownership!D177/Ownership!D178 -> 0 | G9: =Ownership!E177/Ownership!E178 -> 0.20733636 | H9: =F9*D9 -> 0 | I9: =G9*D9 -> 4.9346054 | J9: =Ownership!D172/Ownership!D178 -> 0 | K9: =Ownership!E172/Ownership!E178 -> 0.13822424 | L9: =Ownership!D173/Ownership!D178 -> 0 | M9: =Ownership!E173/Ownership!E178 -> 0.026836089 | N9: =Ownership!D174/Ownership!D178 -> 0 | O9: =Ownership!E174/Ownership!E178 -> 0.011641226 | P9: =Ownership!D175/Ownership!D178 -> 0 | Q9: =Ownership!E175/Ownership!E178 -> 0.0031860197 | R9: =Ownership!D176/Ownership!D178 -> 0 | S9: =Ownership!E176/Ownership!E178 -> 0.019361197 | T9: =J9*$D$9 -> 0 | U9: =K9*$D$9 -> 3.2897369 | V9: =L9*$D$9 -> 0 | W9: =M9*$D$9 -> 0.63869893 | X9: =N9*$D$9 -> 0 | Y9: =O9*$D$9 -> 0.27706118 | Z9: =P9*$D$9 -> 0 | AA9: =Q9*$D$9 -> 0.07582727 | ... AC9: =S9*$D$9 -> 0.46079649 | AD9: Thales | AE9: FR | AF9: 20679.6 | AG9: 57
A10: Alter Technology TUV Nord France | B10: FR | C10: 9.2 | E10: 2 | F10: =Ownership!D250/Ownership!D251 -> 0 | G10: =Ownership!E250/Ownership!E251 -> 0 | H10: =F10*C10 -> 0 | I10: =G10*C10 -> 0 | J10: 0 | K10: 0 | L10: 0 | M10: 0 | N10: 0 | O10: 0 | P10: 0 | Q10: 0 | R10: 0 | S10: 0 | T10: =J10*$C$10 -> 0 | U10: =K10*$C$10 -> 0 | V10: =L10*$C$10 -> 0 | W10: =M10*$C$10 -> 0 | X10: =N10*$C$10 -> 0 | Y10: =O10*$C$10 -> 0 | Z10: =P10*$C$10 -> 0 | AA10: =Q10*$C$10 -> 0 | ... AC10: =S10*$C$10 -> 0 | AD10: TUEV Nord AG | AE10: DE | AF10: 1597.8 | AG10: 3
A11: Alter Technology TUV Nord SA | B11: ES | C11: 46.5 | E11: 1 | F11: =Ownership!D250/Ownership!D251 -> 0 | G11: =Ownership!E250/Ownership!E251 -> 0 | H11: =F11*C11 -> 0 | I11: =G11*C11 -> 0 | J11: 0 | K11: 0 | L11: 0 | M11: 0 | N11: 0 | O11: 0 | P11: 0 | Q11: 0 | R11: 0 | S11: 0 | T11: =J11*$C$11 -> 0 | U11: =K11*$C$11 -> 0 | V11: =L11*$C$11 -> 0 | W11: =M11*$C$11 -> 0 | X11: =N11*$C$11 -> 0 | Y11: =O11*$C$11 -> 0 | Z11: =P11*$C$11 -> 0 | AA11: =Q11*$C$11 -> 0 | ... AC11: =S11*$C$11 -> 0 | AD11: TUEV Nord AG | AE11: DE | AF11: 1597.8 | AG11: 3
A12: Antwerp Space NV | B12: BE | D12: 9.9 | E12: 1 | F12: =Ownership!D110/Ownership!D111 -> 0 | G12: =Ownership!E110/Ownership!E111 -> 0.45922747 | H12: =F12*D12 -> 0 | I12: =G12*D12 -> 4.5463519 | J12: 0 | K12: =Ownership!E105/Ownership!E111 -> 0.15879828 | L12: 0 | M12: =Ownership!E106/Ownership!E111 -> 0 | N12: 0 | O12: =Ownership!E107/Ownership!E111 -> 0.15665236 | P12: 0 | Q12: =Ownership!E108/Ownership!E111 -> 0.14377682 | R12: 0 | S12: =Ownership!E109/Ownership!E111 -> 0 | T12: =J12*$D$12 -> 0 | U12: =K12*$D$12 -> 1.572103 | V12: =L12*$D$12 -> 0 | W12: =M12*$D$12 -> 0 | X12: =N12*$D$12 -> 0 | Y12: =O12*$D$12 -> 1.5508584 | Z12: =P12*$D$12 -> 0 | AA12: =Q12*$D$12 -> 1.4233906 | ... AC12: =S12*$D$12 -> 0 | AD12: OHB SE | AE12: DE | AF12: 1037 | AG12: 18
A13: ArianeGroup GMBH | B13: DE | C13: 326.4 | E13: 1 | F13: =Ownership!D38/Ownership!D39 -> 0 | G13: =Ownership!E38/Ownership!E39 -> 0.13255361 | H13: =F13*C13 -> 0 | I13: =G13*C13 -> 43.265497 | J13: 0 | K13: =Ownership!E33/Ownership!E39 -> 0.043805501 | L13: 0 | M13: =Ownership!E34/Ownership!E39 -> 0 | N13: 0 | O13: =Ownership!E35/Ownership!E39 -> 0.054905783 | P13: 0 | Q13: =Ownership!E36/Ownership!E39 -> 0 | R13: 0 | S13: =Ownership!E37/Ownership!E39 -> 0 | T13: =J13*$C$13 -> 0 | U13: =K13*$C$13 -> 14.298116 | V13: =L13*$C$13 -> 0 | W13: =M13*$C$13 -> 0 | X13: =N13*$C$13 -> 0 | Y13: =O13*$C$13 -> 17.921248 | Z13: =P13*$C$13 -> 0 | AA13: =Q13*$C$13 -> 0 | ... AC13: =S13*$C$13 -> 0 | AD13: ArianeGroup Holding | AE13: FR | AF13: 11.8 | AG13: 2
A14: ArianeGroup SAS | B14: FR | D14: 2243.7 | E14: 1 | F14: =Ownership!D38/Ownership!D39 -> 0 | G14: =Ownership!E38/Ownership!E39 -> 0.13255361 | H14: =F14*D14 -> 0 | I14: =G14*D14 -> 297.41053 | J14: =J13 -> 0 | K14: =K13 -> 0.043805501 | L14: =L13 -> 0 | M14: =M13 -> 0 | N14: =N13 -> 0 | O14: =O13 -> 0.054905783 | P14: =P13 -> 0 | Q14: =Q13 -> 0 | ... S14: =S13 -> 0 | T14: =J14*$D$14 -> 0 | U14: =K14*$D$14 -> 98.286404 | V14: =L14*$D$14 -> 0 | W14: =M14*$D$14 -> 0 | X14: =N14*$D$14 -> 0 | Y14: =O14*$D$14 -> 123.19211 | Z14: =P14*$D$14 -> 0 | AA14: =Q14*$D$14 -> 0 | ... AC14: =S14*$D$14 -> 0 | AD14: ArianeGroup Holding | AE14: FR | AF14: 11.8 | AG14: 2
A15: Arianespace | B15: FR | C15: 1467.8 | E15: 1 | F15: =Ownership!D38/Ownership!D39 -> 0 | G15: =Ownership!E38/Ownership!E39 -> 0.13255361 | H15: =F15*C15 -> 0 | I15: =G15*C15 -> 194.56218 | J15: =J14 -> 0 | K15: =K14 -> 0.043805501 | L15: =L14 -> 0 | M15: =M14 -> 0 | N15: =N14 -> 0 | O15: =O14 -> 0.054905783 | P15: =P14 -> 0 | Q15: =Q14 -> 0 | ... S15: =S14 -> 0 | T15: =J15*$C15 -> 0 | U15: =K15*$C15 -> 64.297715 | V15: =L15*$C15 -> 0 | W15: =M15*$C15 -> 0 | X15: =N15*$C15 -> 0 | Y15: =O15*$C15 -> 80.590708 | Z15: =P15*$C15 -> 0 | AA15: =Q15*$C15 -> 0 | ... AC15: =S15*$C15 -> 0 | AD15: ArianeGroup Holding | AE15: FR | AF15: 11.8 | AG15: 2
A16: Avio SPA | B16: IT | D16: 435.6 | E16: 24 | F16: =Ownership!D310/Ownership!D311 -> 0 | G16: =Ownership!E310/Ownership!E311 -> 0.1270711 | H16: =F16*D16 -> 0 | I16: =G16*D16 -> 55.352171 | J16: 0 | K16: =Ownership!E305/Ownership!E311 -> 0.0745742 | L16: 0 | M16: =Ownership!E306/Ownership!E311 -> 0 | N16: 0 | O16: =Ownership!E307/Ownership!E311 -> 0.019126332 | P16: 0 | Q16: =Ownership!E308/Ownership!E311 -> 0 | R16: 0 | S16: =Ownership!E309/Ownership!E311 -> 0.0087303377 | T16: =J16*$D16 -> 0 | U16: =K16*$D16 -> 32.484521 | V16: =L16*$D16 -> 0 | W16: =M16*$D16 -> 0 | X16: =N16*$D16 -> 0 | Y16: =O16*$D16 -> 8.3314302 | Z16: =P16*$D16 -> 0 | AA16: =Q16*$D16 -> 0 | ... AC16: =S16*$D16 -> 3.8029351
A17: Azur Space Solar Power GMBH | B17: DE | C17: 70.4 | E17: 1 | F17: =Ownership!D320/Ownership!D321 -> 1 | G17: =Ownership!E320/Ownership!E321 -> 1 | H17: =F17*C17 -> 70.4 | I17: =G17*C17 -> 70.4 | J17: 0 | K17: 0 | L17: =Ownership!D316/Ownership!D321 -> 1 | M17: =Ownership!E316/Ownership!E321 -> 1 | N17: 0 | O17: 0 | P17: 0 | Q17: 0 | R17: 0 | S17: 0 | T17: =J17*$C17 -> 0 | U17: =K17*$C17 -> 0 | V17: =L17*$C17 -> 70.4 | W17: =M17*$C17 -> 70.4 | X17: =N17*$C17 -> 0 | Y17: =O17*$C17 -> 0 | Z17: =P17*$C17 -> 0 | AA17: =Q17*$C17 -> 0 | ... AC17: =S17*$C17 -> 0 | AD17: 5N Plus INC | AE17: CA | AF17: - | AG17: n.a.
A18: Beyond Gravity Austria GMBH (RUAG Space GMBH) | B18: AT | C18: 56.2 | E18: 2 | F18: =Ownership!D660/Ownership!D661 -> 0 | G18: =Ownership!E660/Ownership!E661 -> 0 | H18: =F18*C18 -> 0 | I18: =G18*C18 -> 0 | J18: 0 | K18: 0 | L18: 0 | M18: 0 | N18: 0 | O18: 0 | P18: 0 | Q18: 0 | R18: 0 | S18: 0 | T18: =J18*$C18 -> 0 | U18: =K18*$C18 -> 0 | V18: =L18*$C18 -> 0 | W18: =M18*$C18 -> 0 | X18: =N18*$C18 -> 0 | Y18: =O18*$C18 -> 0 | Z18: =P18*$C18 -> 0 | AA18: =Q18*$C18 -> 0 | ... AC18: =S18*$C18 -> 0 | AD18: Schweizerische Eidgenossenschaft | AE18: CH | AF18: - | AG18: -
A19: Beyond Gravity Sweden AB (RUAG Space AB) | B19: SE | C19: 88.4 | E19: 1 | F19: =Ownership!D671/Ownership!D672 -> 0 | G19: =Ownership!E671/Ownership!E672 -> 1 | H19: =F19*C19 -> 0 | I19: =G19*C19 -> 88.4 | J19: 0 | K19: 0 | L19: 0 | M19: 0 | N19: 0 | O19: 0 | P19: 0 | Q19: =Ownership!E669/Ownership!E672 -> 1 | R19: 0 | S19: 0 | T19: =J19*$C19 -> 0 | U19: =K19*$C19 -> 0 | V19: =L19*$C19 -> 0 | W19: =M19*$C19 -> 0 | X19: =N19*$C19 -> 0 | Y19: =O19*$C19 -> 0 | Z19: =P19*$C19 -> 0 | AA19: =Q19*$C19 -> 88.4 | ... AC19: =S19*$C19 -> 0 | AD19: Schweizerische Eidgenossenschaft | AE19: CH | AF19: - | AG19: -
A20: CGI Deutschland BV & CO.KG | B20: DE | C20: 634.4 | E20: 2 | F20: =Ownership!D895/Ownership!D896 -> 1 | G20: =Ownership!E895/Ownership!E896 -> 0.98251963 | H20: =F20*C20 -> 634.4 | I20: =G20*C20 -> 623.31045 | J20: =Ownership!D890/Ownership!D896 -> 0.088998764 | K20: =Ownership!E890/Ownership!E896 -> 0.12854882 | L20: =Ownership!D891/Ownership!D896 -> 0.81307513 | M20: =Ownership!E891/Ownership!E896 -> 0.68210558 | N20: =Ownership!D892/Ownership!D896 -> 0 | O20: =Ownership!E892/Ownership!E896 -> 0.017480374 | P20: =Ownership!D893/Ownership!D896 -> 0 | Q20: =Ownership!E893/Ownership!E896 -> 0.01311028 | R20: =Ownership!D894/Ownership!D896 -> 0 | S20: =Ownership!E894/Ownership!E896 -> 0.015521366 | T20: =J20*$C20 -> 56.460816 | U20: =K20*$C20 -> 81.551368 | V20: =L20*$C20 -> 515.81486 | W20: =M20*$C20 -> 432.72778 | X20: =N20*$C20 -> 0 | Y20: =O20*$C20 -> 11.089549 | Z20: =P20*$C20 -> 0 | AA20: =Q20*$C20 -> 8.3171619 | ... AC20: =S20*$C20 -> 9.8467548 | AD20: CGI INC | AE20: CA | AF20: 9387.3 | AG20: 89
A21: CS Group - Germany GMBH | B21: DE | E21: 1 | F21: =Ownership!D972/Ownership!D973 -> 0.012942282 | G21: =Ownership!E972/Ownership!E973 -> 0.30248307 | H21: =F21*C21 -> 0 | I21: =G21*C21 -> 0 | J21: =Ownership!D967/Ownership!D973 -> 0 | K21: =Ownership!E967/Ownership!E973 -> 0.16301193 | L21: =Ownership!D968/Ownership!D973 -> 0.012942282 | M21: =Ownership!E968/Ownership!E973 -> 0.0058045792 | N21: =Ownership!D969/Ownership!D973 -> 0 | O21: =Ownership!E969/Ownership!E973 -> 0.0090293454 | P21: =Ownership!D970/Ownership!D973 -> 0 | Q21: =Ownership!E970/Ownership!E973 -> 0.0041921961 | R21: =Ownership!D971/Ownership!D973 -> 0 | S21: =Ownership!E971/Ownership!E973 -> 0.032570139 | T21: =J21*$C21 -> 0 | U21: =K21*$C21 -> 0 | V21: =L21*$C21 -> 0 | W21: =M21*$C21 -> 0 | X21: =N21*$C21 -> 0 | Y21: =O21*$C21 -> 0 | Z21: =P21*$C21 -> 0 | AA21: =Q21*$C21 -> 0 | ... AC21: =S21*$C21 -> 0 | AD21: Sopra Steria Group SA | AE21: FR | AF21: 5460.6 | AG21: 66
A22: CS Group - Romania SA | B22: RO | D22: 4.4 | E22: 4 | F22: =Ownership!D972/Ownership!D973 -> 0.012942282 | G22: =Ownership!E972/Ownership!E973 -> 0.30248307 | H22: =F22*D22 -> 0.056946039 | I22: =G22*D22 -> 1.3309255 | J22: =J21 -> 0 | K22: =K21 -> 0.16301193 | L22: =L21 -> 0.012942282 | M22: =M21 -> 0.0058045792 | N22: =N21 -> 0 | O22: =O21 -> 0.0090293454 | P22: =P21 -> 0 | Q22: =Q21 -> 0.0041921961 | ... S22: =S21 -> 0.032570139 | T22: =J22*$D22 -> 0 | U22: =K22*$D22 -> 0.7172525 | V22: =L22*$D22 -> 0.056946039 | W22: =M22*$D22 -> 0.025540148 | X22: =N22*$D22 -> 0 | Y22: =O22*$D22 -> 0.03972912 | Z22: =P22*$D22 -> 0 | AA22: =Q22*$D22 -> 0.018445663 | ... AC22: =S22*$D22 -> 0.14330861 | AD22: Sopra Steria Group SA | AE22: FR | AF22: 5460.6 | AG22: 66
A23: CS Group France | B23: FR | D23: 221.6 | E23: 3 | F23: =Ownership!D972/Ownership!D973 -> 0.012942282 | G23: =Ownership!E972/Ownership!E973 -> 0.30248307 | H23: =F23*D23 -> 2.8680096 | I23: =G23*D23 -> 67.030248 | J23: =J22 -> 0 | K23: =K22 -> 0.16301193 | L23: =L22 -> 0.012942282 | M23: =M22 -> 0.0058045792 | N23: =N22 -> 0 | O23: =O22 -> 0.0090293454 | P23: =P22 -> 0 | Q23: =Q22 -> 0.0041921961 | ... S23: =S22 -> 0.032570139 | T23: =J23*$D23 -> 0 | U23: =K23*$D23 -> 36.123444 | V23: =L23*$D23 -> 2.8680096 | W23: =M23*$D23 -> 1.2862947 | X23: =N23*$D23 -> 0 | Y23: =O23*$D23 -> 2.0009029 | Z23: =P23*$D23 -> 0 | AA23: =Q23*$D23 -> 0.92899065 | ... AC23: =S23*$D23 -> 7.2175427 | AD23: Sopra Steria Group SA | AE23: FR | AF23: 5460.6 | AG23: 66
A24: Dassault Aviation | B24: FR | D24: 7569.4 | E24: 29 | F24: =Ownership!D365/Ownership!D366 -> 0 | G24: =Ownership!E365/Ownership!E366 -> 0.1145923 | H24: =F24*D24 -> 0 | I24: =G24*D24 -> 867.39494 | J24: 0 | K24: =Ownership!E360/Ownership!E366 -> 0.087344529 | L24: 0 | M24: =Ownership!E361/Ownership!E366 -> 0.0040287881 | N24: 0 | O24: =Ownership!E362/Ownership!E366 -> 0.010058272 | P24: 0 | Q24: 0 | R24: 0 | S24: =Ownership!E364/Ownership!E366 -> 0.0095347985 | T24: =J24*$D24 -> 0 | U24: =K24*$D24 -> 661.14568 | V24: =L24*$D24 -> 0 | W24: =M24*$D24 -> 30.495509 | X24: =N24*$D24 -> 0 | Y24: =O24*$D24 -> 76.135087 | Z24: =P24*$D24 -> 0 | AA24: =Q24*$D24 -> 0 | ... AC24: =S24*$D24 -> 72.172704 | AD24: Rond Point Immobilier | AE24: FR | AF24: 1132.6 | AG24: 16
A25: Deimos Engenharia | B25: PT | D25: 7.8 | E25: 2 | F25: =Ownership!D381/Ownership!D382 -> 0 | G25: =Ownership!E381/Ownership!E382 -> 0 | H25: =F25*D25 -> 0 | I25: =G25*D25 -> 0 | J25: 0 | K25: 0 | L25: 0 | M25: 0 | N25: 0 | O25: 0 | P25: 0 | Q25: 0 | R25: 0 | S25: 0 | T25: =J25*$D25 -> 0 | U25: =K25*$D25 -> 0 | V25: =L25*$D25 -> 0 | W25: =M25*$D25 -> 0 | X25: =N25*$D25 -> 0 | Y25: =O25*$D25 -> 0 | Z25: =P25*$D25 -> 0 | AA25: =Q25*$D25 -> 0 | ... AC25: =S25*$D25 -> 0 | AD25: Cantiles XXI SL | AE25: FR | AF25: 3563.5 | AG25: 3
A26: Deimos Space Romania | B26: RO | D26: 1.5 | E26: 1 | F26: =Ownership!D381/Ownership!D382 -> 0 | G26: =Ownership!E381/Ownership!E382 -> 0 | H26: =F26*D26 -> 0 | I26: =G26*D26 -> 0 | J26: 0 | K26: 0 | L26: 0 | M26: 0 | N26: 0 | O26: 0 | P26: 0 | Q26: 0 | R26: 0 | S26: 0 | T26: =J26*$D26 -> 0 | U26: =K26*$D26 -> 0 | V26: =L26*$D26 -> 0 | W26: =M26*$D26 -> 0 | X26: =N26*$D26 -> 0 | Y26: =O26*$D26 -> 0 | Z26: =P26*$D26 -> 0 | AA26: =Q26*$D26 -> 0 | ... AC26: =S26*$D26 -> 0 | AD26: Cantiles XXI SL | AE26: ES | AF26: 3563.5 | AG26: 3
A27: Deimos Space, Sociedad Limitada Unipersonal | B27: ES | C27: 30.2 | E27: 1 | F27: =Ownership!D381/Ownership!D382 -> 0 | G27: =Ownership!E381/Ownership!E382 -> 0 | H27: =F27*C27 -> 0 | I27: =G27*C27 -> 0 | J27: 0 | K27: 0 | L27: 0 | M27: 0 | N27: 0 | O27: 0 | P27: 0 | Q27: 0 | R27: 0 | S27: 0 | T27: =J27*$C27 -> 0 | U27: =K27*$C27 -> 0 | V27: =L27*$C27 -> 0 | W27: =M27*$C27 -> 0 | X27: =N27*$C27 -> 0 | Y27: =O27*$C27 -> 0 | Z27: =P27*$C27 -> 0 | AA27: =Q27*$C27 -> 0 | ... AC27: =S27*$C27 -> 0 | AD27: Cantiles XXI SL | AE27: ES | AF27: 3563.5 | AG27: 3
A28: e-GEOS SPA | B28: IT | C28: 89.7 | E28: 2 | F28: =Ownership!D594/Ownership!D595 -> 0.2596837 | G28: =Ownership!E594/Ownership!E595 -> 0.4490146 | H28: =F28*C28 -> 23.293628 | I28: =G28*C28 -> 40.27661 | J28: =Ownership!D589/Ownership!D595 -> 0.14852166 | K28: =Ownership!E589/Ownership!E595 -> 0.35688152 | L28: =Ownership!D590/Ownership!D595 -> 0 | M28: =Ownership!E590/Ownership!E595 -> 0 | N28: =Ownership!D591/Ownership!D595 -> 0.076323631 | O28: =Ownership!E591/Ownership!E595 -> 0.02564311 | P28: =Ownership!D592/Ownership!D595 -> 0 | Q28: =Ownership!E592/Ownership!E595 -> 0.0032521383 | R28: =Ownership!D593/Ownership!D595 -> 0.034838414 | S28: =Ownership!E593/Ownership!E595 -> 0.052196819 | T28: =J28*$C28 -> 13.322393 | U28: =K28*$C28 -> 32.012273 | V28: =L28*$C28 -> 0 | W28: =M28*$C28 -> 0 | X28: =N28*$C28 -> 6.8462297 | Y28: =O28*$C28 -> 2.300187 | Z28: =P28*$C28 -> 0 | AA28: =Q28*$C28 -> 0.2917168 | ... AC28: =S28*$C28 -> 4.6820547 | AD28: Leonardo SPA | AE28: IT | AF28: 16515.2 | AG28: 47
A29: Elecnor Infrastrutture e Aerospaziale | B29: IT | C29: 1.6 | E29: 2 | F29: =Ownership!D381/Ownership!D382 -> 0 | G29: =Ownership!E381/Ownership!E382 -> 0 | H29: =F29*C29 -> 0 | I29: =G29*C29 -> 0 | J29: 0 | K29: 0 | L29: 0 | M29: 0 | N29: 0 | O29: 0 | P29: 0 | Q29: 0 | R29: 0 | S29: 0 | T29: =J29*$C29 -> 0 | U29: =K29*$C29 -> 0 | V29: =L29*$C29 -> 0 | W29: =M29*$C29 -> 0 | X29: =N29*$C29 -> 0 | Y29: =O29*$C29 -> 0 | Z29: =P29*$C29 -> 0 | AA29: =Q29*$C29 -> 0 | ... AC29: =S29*$C29 -> 0 | AD29: Cantiles XXI SL | AE29: ES | AF29: 3563.5 | AG29: 3
A30: Enpulsion GMBH | B30: AT | E30: 8 | F30: =Ownership!D59/Ownership!D60 -> 0 | G30: =Ownership!E59/Ownership!E60 -> 0 | H30: =F30*C30 -> 0 | I30: =G30*C30 -> 0 | J30: 0 | K30: 0 | L30: 0 | M30: 0 | N30: 0 | O30: 0 | P30: 0 | Q30: 0 | R30: 0 | S30: 0 | T30: =J30*$C30 -> 0 | U30: =K30*$C30 -> 0 | V30: =L30*$C30 -> 0 | W30: =M30*$C30 -> 0 | X30: =N30*$C30 -> 0 | Y30: =O30*$C30 -> 0 | Z30: =P30*$C30 -> 0 | AA30: =Q30*$C30 -> 0 | ... AC30: =S30*$C30 -> 0 | AD30: mr Alexander Reissner
A31: GMV Aerospace & Defence SA | B31: ES | C31: 186.5 | E31: 1 | F31: =Ownership!D394/Ownership!D395 -> 0 | G31: =Ownership!E394/Ownership!E395 -> 0 | H31: =F31*C31 -> 0 | I31: =G31*C31 -> 0 | J31: 0 | K31: 0 | L31: 0 | M31: 0 | N31: 0 | O31: 0 | P31: 0 | Q31: 0 | R31: 0 | S31: 0 | T31: =J31*$C31 -> 0 | U31: =K31*$C31 -> 0 | V31: =L31*$C31 -> 0 | W31: =M31*$C31 -> 0 | X31: =N31*$C31 -> 0 | Y31: =O31*$C31 -> 0 | Z31: =P31*$C31 -> 0 | AA31: =Q31*$C31 -> 0 | ... AC31: =S31*$C31 -> 0 | AD31: GMV Innovating Solutions SL | AE31: ES | AF31: 288.2 | AG31: 2
A32: GMV GMBH | B32: DE | C32: 24.9 | E32: 1 | F32: =Ownership!D394/Ownership!D395 -> 0 | G32: =Ownership!E394/Ownership!E395 -> 0 | H32: =F32*C32 -> 0 | I32: =G32*C32 -> 0 | J32: 0 | K32: 0 | L32: 0 | M32: 0 | N32: 0 | O32: 0 | P32: 0 | Q32: 0 | R32: 0 | S32: 0 | T32: =J32*$C32 -> 0 | U32: =K32*$C32 -> 0 | V32: =L32*$C32 -> 0 | W32: =M32*$C32 -> 0 | X32: =N32*$C32 -> 0 | Y32: =O32*$C32 -> 0 | Z32: =P32*$C32 -> 0 | AA32: =Q32*$C32 -> 0 | ... AC32: =S32*$C32 -> 0 | AD32: GMV Innovating Solutions SL | AE32: ES | AF32: 288.2 | AG32: 2
A33: GMV Innovating Solutions BV | B33: NL | E33: 1 | F33: =Ownership!D394/Ownership!D395 -> 0 | G33: =Ownership!E394/Ownership!E395 -> 0 | H33: =F33*C33 -> 0 | I33: =G33*C33 -> 0 | J33: 0 | K33: 0 | L33: 0 | M33: 0 | N33: 0 | O33: 0 | P33: 0 | Q33: 0 | R33: 0 | S33: 0 | T33: =J33*$C33 -> 0 | U33: =K33*$C33 -> 0 | V33: =L33*$C33 -> 0 | W33: =M33*$C33 -> 0 | X33: =N33*$C33 -> 0 | Y33: =O33*$C33 -> 0 | Z33: =P33*$C33 -> 0 | AA33: =Q33*$C33 -> 0 | ... AC33: =S33*$C33 -> 0 | AD33: GMV Innovating Solutions SL | AE33: ES | AF33: 288.2 | AG33: 2
A34: GMV Innovating Solutions SARL | B34: FR | D34: 8.6 | E34: 3 | F34: =Ownership!D394/Ownership!D395 -> 0 | G34: =Ownership!E394/Ownership!E395 -> 0 | H34: =F34*D34 -> 0 | I34: =G34*D34 -> 0 | J34: 0 | K34: 0 | L34: 0 | M34: 0 | N34: 0 | O34: 0 | P34: 0 | Q34: 0 | R34: 0 | S34: 0 | T34: =J34*$D34 -> 0 | U34: =K34*$D34 -> 0 | V34: =L34*$D34 -> 0 | W34: =M34*$D34 -> 0 | X34: =N34*$D34 -> 0 | Y34: =O34*$D34 -> 0 | Z34: =P34*$D34 -> 0 | AA34: =Q34*$D34 -> 0 | ... AC34: =S34*$D34 -> 0 | AD34: GMV Innovating Solutions SL | AE34: ES | AF34: 288.2 | AG34: 2
A35: GMV Innovating Solutions Sp.z o.o. | B35: PL | D35: 8.7 | E35: 1 | F35: =Ownership!D394/Ownership!D395 -> 0 | G35: =Ownership!E394/Ownership!E395 -> 0 | H35: =F35*D35 -> 0 | I35: =G35*D35 -> 0 | J35: 0 | K35: 0 | L35: 0 | M35: 0 | N35: 0 | O35: 0 | P35: 0 | Q35: 0 | R35: 0 | S35: 0 | T35: =J35*$D35 -> 0 | U35: =K35*$D35 -> 0 | V35: =L35*$D35 -> 0 | W35: =M35*$D35 -> 0 | X35: =N35*$D35 -> 0 | Y35: =O35*$D35 -> 0 | Z35: =P35*$D35 -> 0 | AA35: =Q35*$D35 -> 0 | ... AC35: =S35*$D35 -> 0 | AD35: GMV Innovating Solutions SL | AE35: ES | AF35: 288.2 | AG35: 2
A36: GMV Innovating Solutions SRL | B36: RO | D36: 5.5 | E36: 1 | F36: =Ownership!D394/Ownership!D395 -> 0 | G36: =Ownership!E394/Ownership!E395 -> 0 | H36: =F36*D36 -> 0 | I36: =G36*D36 -> 0 | J36: 0 | K36: 0 | L36: 0 | M36: 0 | N36: 0 | O36: 0 | P36: 0 | Q36: 0 | R36: 0 | S36: 0 | T36: =J36*$D36 -> 0 | U36: =K36*$D36 -> 0 | V36: =L36*$D36 -> 0 | W36: =M36*$D36 -> 0 | X36: =N36*$D36 -> 0 | Y36: =O36*$D36 -> 0 | Z36: =P36*$D36 -> 0 | AA36: =Q36*$D36 -> 0 | ... AC36: =S36*$D36 -> 0 | AD36: GMV Innovating Solutions SL | AE36: ES | AF36: 288.2 | AG36: 2
A37: GMV Innovating Solutions SRL (B) | B37: BE | E37: 1 | F37: =Ownership!D394/Ownership!D395 -> 0 | G37: =Ownership!E394/Ownership!E395 -> 0 | H37: =F37*C37 -> 0 | I37: =G37*C37 -> 0 | J37: 0 | K37: 0 | L37: 0 | M37: 0 | N37: 0 | O37: 0 | P37: 0 | Q37: 0 | R37: 0 | S37: 0 | T37: =J37*$C37 -> 0 | U37: =K37*$C37 -> 0 | V37: =L37*$C37 -> 0 | W37: =M37*$C37 -> 0 | X37: =N37*$C37 -> 0 | Y37: =O37*$C37 -> 0 | Z37: =P37*$C37 -> 0 | AA37: =Q37*$C37 -> 0 | ... AC37: =S37*$C37 -> 0 | AD37: GMV Innovating Solutions SL | AE37: ES | AF37: 288.2 | AG37: 2
A38: GMV Soluciones Globales Internet SA | B38: ES | C38: 56 | E38: 1 | F38: =Ownership!D394/Ownership!D395 -> 0 | G38: =Ownership!E394/Ownership!E395 -> 0 | H38: =F38*C38 -> 0 | I38: =G38*C38 -> 0 | J38: 0 | K38: 0 | L38: 0 | M38: 0 | N38: 0 | O38: 0 | P38: 0 | Q38: 0 | R38: 0 | S38: 0 | T38: =J38*$C38 -> 0 | U38: =K38*$C38 -> 0 | V38: =L38*$C38 -> 0 | W38: =M38*$C38 -> 0 | X38: =N38*$C38 -> 0 | Y38: =O38*$C38 -> 0 | Z38: =P38*$C38 -> 0 | AA38: =Q38*$C38 -> 0 | ... AC38: =S38*$C38 -> 0 | AD38: GMV Innovating Solutions SL | AE38: ES | AF38: 288 | AG38: 2
A39: GMVIS Skysoft SA | B39: PT | D39: 9.5 | E39: 1 | F39: =Ownership!D394/Ownership!D395 -> 0 | G39: =Ownership!E394/Ownership!E395 -> 0 | H39: =F39*D39 -> 0 | I39: =G39*D39 -> 0 | J39: 0 | K39: 0 | L39: 0 | M39: 0 | N39: 0 | O39: 0 | P39: 0 | Q39: 0 | R39: 0 | S39: 0 | T39: =J39*$D39 -> 0 | U39: =K39*$D39 -> 0 | V39: =L39*$D39 -> 0 | W39: =M39*$D39 -> 0 | X39: =N39*$D39 -> 0 | Y39: =O39*$D39 -> 0 | Z39: =P39*$D39 -> 0 | AA39: =Q39*$D39 -> 0 | ... AC39: =S39*$D39 -> 0 | AD39: GMV Innovating Solutions SL | AE39: ES | AF39: 288.2 | AG39: 2
A40: Indra Sistemas SA | B40: ES | C40: 3864.2 | E40: 148 | F40: =Ownership!D501/Ownership!D502 -> 0.36546339 | G40: =Ownership!E501/Ownership!E502 -> 0.57145585 | H40: =F40*C40 -> 1412.2236 | I40: =G40*C40 -> 2208.2197 | J40: =Ownership!D496/Ownership!D502 -> 0.18010753 | K40: =Ownership!E496/Ownership!E502 -> 0.34830855 | L40: =Ownership!D497/Ownership!D502 -> 0.00025601639 | M40: =Ownership!E497/Ownership!E502 -> 0.0054638327 | N40: =Ownership!D498/Ownership!D502 -> 0.10023041 | O40: =Ownership!E498/Ownership!E502 -> 0.006010216 | P40: =Ownership!D499/Ownership!D502 -> 0 | Q40: =Ownership!E499/Ownership!E502 -> 0.0033875763 | R40: =Ownership!D500/Ownership!D502 -> 0.034178187 | S40: =Ownership!E500/Ownership!E502 -> 0.061959863 | T40: =J40*$C40 -> 695.97151 | U40: =K40*$C40 -> 1345.9339 | V40: =L40*$C40 -> 0.98929852 | W40: =M40*$C40 -> 21.113342 | X40: =N40*$C40 -> 387.31037 | Y40: =O40*$C40 -> 23.224677 | Z40: =P40*$C40 -> 0 | AA40: =Q40*$C40 -> 13.090272 | ... AC40: =S40*$C40 -> 239.4253
A41: Loft Orbital Technologies | B41: FR | D41: 18.9 | E41: 7 | F41: =Ownership!D983/Ownership!D984 -> 1 | G41: =Ownership!E983/Ownership!E984 -> 0 | H41: =F41*D41 -> 18.9 | I41: =G41*D41 -> 0 | J41: =Ownership!D978/Ownership!D984 -> 1 | K41: 0 | L41: 0 | M41: 0 | N41: 0 | O41: 0 | P41: 0 | Q41: 0 | R41: 0 | S41: 0 | T41: =J41*$D41 -> 18.9 | U41: =K41*$D41 -> 0 | V41: =L41*$D41 -> 0 | W41: =M41*$D41 -> 0 | X41: =N41*$D41 -> 0 | Y41: =O41*$D41 -> 0 | Z41: =P41*$D41 -> 0 | AA41: =Q41*$D41 -> 0 | ... AC41: =S41*$D41 -> 0 | AD41: mr Antoine Francois Benoit Bellon de Chassy | AE41: FR | AF41: - | AG41: -
A42: MOLTEK | B42: NL | H42: =F42*C42 -> 0 | I42: =G42*C42 -> 0 | T42: =J42*$C42 -> 0 | U42: =K42*$C42 -> 0 | V42: =L42*$C42 -> 0 | W42: =M42*$C42 -> 0 | X42: =N42*$C42 -> 0 | Y42: =O42*$C42 -> 0 | Z42: =P42*$C42 -> 0 | AA42: =Q42*$C42 -> 0 | ... AC42: =S42*$C42 -> 0
A43: MT Aerospace AG | B43: DE | C43: 112.7 | E43: 1 | F43: =Ownership!D995/Ownership!D996 -> 0 | G43: =Ownership!E995/Ownership!E996 -> 0 | H43: =F43*C43 -> 0 | I43: =G43*C43 -> 0 | J43: 0 | K43: 0 | L43: 0 | M43: 0 | N43: 0 | O43: 0 | P43: 0 | Q43: 0 | R43: 0 | S43: 0 | T43: =J43*$C43 -> 0 | U43: =K43*$C43 -> 0 | V43: =L43*$C43 -> 0 | W43: =M43*$C43 -> 0 | X43: =N43*$C43 -> 0 | Y43: =O43*$C43 -> 0 | Z43: =P43*$C43 -> 0 | AA43: =Q43*$C43 -> 0 | ... AC43: =S43*$C43 -> 0 | AD43: MT Aerospace Holding GMBH | AE43: DE | AF43: - | AG43: 2
A44: Neuraspace | B44: PT | C44: 0.3 | E44: 3 | F44: =Ownership!D1007/Ownership!D1008 -> 0 | G44: =Ownership!E1007 -> 0 | H44: =F44*C44 -> 0 | I44: =G44*C44 -> 0 | J44: 0 | K44: 0 | L44: 0 | M44: 0 | N44: 0 | O44: 0 | P44: 0 | Q44: 0 | R44: 0 | S44: 0 | T44: =J44*$C44 -> 0 | U44: =K44*$C44 -> 0 | V44: =L44*$C44 -> 0 | W44: =M44*$C44 -> 0 | X44: =N44*$C44 -> 0 | Y44: =O44*$C44 -> 0 | Z44: =P44*$C44 -> 0 | AA44: =Q44*$C44 -> 0 | ... AC44: =S44*$C44 -> 0 | AD44: mr Paulo Jorge Pimenta Marqeus | AE44: - | AF44: - | AG44: -
A45: OHB Italia | B45: IT | C45: 100.7 | E45: 1 | F45: =Ownership!D110/Ownership!D111 -> 0 | G45: =Ownership!E110/Ownership!E111 -> 0.45922747 | H45: =F45*C45 -> 0 | I45: =G45*C45 -> 46.244206 | J45: 0 | K45: =Ownership!E105/Ownership!E111 -> 0.15879828 | L45: 0 | M45: =Ownership!E106/Ownership!E111 -> 0 | N45: 0 | O45: =Ownership!E107/Ownership!E111 -> 0.15665236 | P45: 0 | Q45: =Ownership!E108/Ownership!E111 -> 0.14377682 | R45: 0 | S45: =Ownership!E109/Ownership!E111 -> 0 | T45: =J45*$C45 -> 0 | U45: =K45*$C45 -> 15.990987 | V45: =L45*$C45 -> 0 | W45: =M45*$C45 -> 0 | X45: =N45*$C45 -> 0 | Y45: =O45*$C45 -> 15.774893 | Z45: =P45*$C45 -> 0 | AA45: =Q45*$C45 -> 14.478326 | ... AC45: =S45*$C45 -> 0 | AD45: OHB SE | AE45: DE | AF45: 1037 | AG45: 18
A46: OHB SE | B46: DE | C46: 1037 | E46: 18 | F46: =Ownership!D110/Ownership!D111 -> 0 | G46: =Ownership!E110/Ownership!E111 -> 0.45922747 | H46: =F46*C46 -> 0 | I46: =G46*C46 -> 476.21888 | J46: 0 | K46: =K45 -> 0.15879828 | L46: =L45 -> 0 | M46: =M45 -> 0 | N46: =N45 -> 0 | O46: =O45 -> 0.15665236 | P46: =P45 -> 0 | Q46: =Q45 -> 0.14377682 | R46: =R45 -> 0 | S46: =S45 -> 0 | T46: =J46*$C46 -> 0 | U46: =K46*$C46 -> 164.67382 | V46: =L46*$C46 -> 0 | W46: =M46*$C46 -> 0 | X46: =N46*$C46 -> 0 | Y46: =O46*$C46 -> 162.4485 | Z46: =P46*$C46 -> 0 | AA46: =Q46*$C46 -> 149.09657 | ... AC46: =S46*$C46 -> 0 | AD46: Familienpool Fuchs
A47: Pangea Aerospace | B47: ES | C47: 0.1 | E47: 1 | F47: =Ownership!D1018/Ownership!D1019 -> 0 | G47: =Ownership!E1018 -> 0 | H47: =F47*C47 -> 0 | I47: =G47*C47 -> 0 | J47: 0 | K47: 0 | L47: 0 | M47: 0 | N47: 0 | O47: 0 | P47: 0 | Q47: 0 | R47: 0 | S47: 0 | T47: =J47*$C47 -> 0 | U47: =K47*$C47 -> 0 | V47: =L47*$C47 -> 0 | W47: =M47*$C47 -> 0 | X47: =N47*$C47 -> 0 | Y47: =O47*$C47 -> 0 | Z47: =P47*$C47 -> 0 | AA47: =Q47*$C47 -> 0 | ... AC47: =S47*$C47 -> 0
A48: RHEA Group Technologies | B48: BE | D48: 2.2 | E48: 1 | H48: =F48*D48 -> 0 | I48: =G48*D48 -> 0 | T48: =J48*$D48 -> 0 | U48: =K48*$D48 -> 0 | V48: =L48*$D48 -> 0 | W48: =M48*$D48 -> 0 | X48: =N48*$D48 -> 0 | Y48: =O48*$D48 -> 0 | Z48: =P48*$D48 -> 0 | AA48: =Q48*$D48 -> 0 | ... AC48: =S48*$D48 -> 0 | AD48: ADGA RHEA Consultants SA | AE48: LU | AF48: - | AG48: -
A49: SABCA | B49: BE | C49: 165.8 | E49: 1 | F49: =Ownership!D683/Ownership!D684 -> 0 | G49: =Ownership!E683/Ownership!E684 -> 0 | H49: =F49*C49 -> 0 | I49: =G49*C49 -> 0 | J49: 0 | K49: 0 | L49: 0 | M49: 0 | N49: 0 | O49: 0 | P49: 0 | Q49: 0 | R49: 0 | S49: 0 | T49: =J49*$C49 -> 0 | U49: =K49*$C49 -> 0 | V49: =L49*$C49 -> 0 | W49: =M49*$C49 -> 0 | X49: =N49*$C49 -> 0 | Y49: =O49*$C49 -> 0 | Z49: =P49*$C49 -> 0 | AA49: =Q49*$C49 -> 0 | ... AC49: =S49*$C49 -> 0 | AD49: BETRIX | AE49: BE | AF49: - | AG49: -
A50: Safran Aero Boosters | B50: BE | D50: 705.6 | E50: 3 | F50: =Ownership!D821/Ownership!D822 -> 0.2753897 | G50: =Ownership!E821/Ownership!E822 -> 0.57736713 | H50: =F50*D50 -> 194.31497 | I50: =G50*D50 -> 407.39025 | J50: =Ownership!D816/Ownership!D822 -> 0.095536136 | K50: =Ownership!E816/Ownership!E822 -> 0.2701516 | L50: =Ownership!D817/Ownership!D822 -> 0 | M50: =Ownership!E817/Ownership!E822 -> 0.024081019 | N50: =Ownership!D818/Ownership!D822 -> 0.11856401 | O50: =Ownership!E818/Ownership!E822 -> 0.14760008 | P50: =Ownership!D819/Ownership!D822 -> 0 | Q50: =Ownership!E819/Ownership!E822 -> 0.0022734558 | R50: =Ownership!D820/Ownership!D822 -> 0 | S50: =Ownership!E820/Ownership!E822 -> 0.0029016476 | T50: =J50*$D50 -> 67.410298 | U50: =K50*$D50 -> 190.61897 | V50: =L50*$D50 -> 0 | W50: =M50*$D50 -> 16.991567 | X50: =N50*$D50 -> 83.658762 | Y50: =O50*$D50 -> 104.14661 | Z50: =P50*$D50 -> 0 | AA50: =Q50*$D50 -> 1.6041504 | ... AC50: =S50*$D50 -> 2.0474025 | AD50: Safran | AE50: FR | AF50: 18434.2 | AG50: 80
A51: Safran Aircraft Engines | B51: FR | C51: 11.9 | E51: 2 | F51: =Ownership!D821/Ownership!D822 -> 0.2753897 | G51: =Ownership!E821/Ownership!E822 -> 0.57736713 | H51: =F51*C51 -> 3.2771375 | I51: =G51*C51 -> 6.8706689 | J51: =J$50 -> 0.095536136 | K51: =K$50 -> 0.2701516 | L51: =L$50 -> 0 | M51: =M$50 -> 0.024081019 | N51: =N$50 -> 0.11856401 | O51: =O$50 -> 0.14760008 | P51: =P$50 -> 0 | Q51: =Q$50 -> 0.0022734558 | ... S51: =S$50 -> 0.0029016476 | T51: =J51*$C51 -> 1.13688 | U51: =K51*$C51 -> 3.214804 | V51: =L51*$C51 -> 0 | W51: =M51*$C51 -> 0.28656412 | X51: =N51*$C51 -> 1.4109117 | Y51: =O51*$C51 -> 1.7564409 | Z51: =P51*$C51 -> 0 | AA51: =Q51*$C51 -> 0.027054124 | ... AC51: =S51*$C51 -> 0.034529606 | AD51: Safran | AE51: FR | AF51: 18434.2 | AG51: 80
A52: Safran Data Systems | B52: FR | C52: 163.7 | E52: 2 | F52: =Ownership!D821/Ownership!D822 -> 0.2753897 | G52: =Ownership!E821/Ownership!E822 -> 0.57736713 | H52: =F52*C52 -> 45.081294 | I52: =G52*C52 -> 94.515 | J52: =J$50 -> 0.095536136 | K52: =K$50 -> 0.2701516 | L52: =L$50 -> 0 | M52: =M$50 -> 0.024081019 | N52: =N$50 -> 0.11856401 | O52: =O$50 -> 0.14760008 | P52: =P$50 -> 0 | Q52: =Q$50 -> 0.0022734558 | ... S52: =S$50 -> 0.0029016476 | T52: =J52*$C52 -> 15.639265 | U52: =K52*$C52 -> 44.223817 | V52: =L52*$C52 -> 0 | W52: =M52*$C52 -> 3.9420627 | X52: =N52*$C52 -> 19.408928 | Y52: =O52*$C52 -> 24.162132 | Z52: =P52*$C52 -> 0 | AA52: =Q52*$C52 -> 0.37216472 | ... AC52: =S52*$C52 -> 0.47499971 | AD52: Safran | AE52: FR | AF52: 18434.2 | AG52: 80
A53: Safran Electrical & Power | B53: FR | C53: 725.8 | E53: 1 | F53: =Ownership!D821/Ownership!D822 -> 0.2753897 | G53: =Ownership!E821/Ownership!E822 -> 0.57736713 | H53: =F53*C53 -> 199.87785 | I53: =G53*C53 -> 419.05306 | J53: =J$50 -> 0.095536136 | K53: =K$50 -> 0.2701516 | L53: =L$50 -> 0 | M53: =M$50 -> 0.024081019 | N53: =N$50 -> 0.11856401 | O53: =O$50 -> 0.14760008 | P53: =P$50 -> 0 | Q53: =Q$50 -> 0.0022734558 | ... S53: =S$50 -> 0.0029016476 | T53: =J53*$C53 -> 69.340128 | U53: =K53*$C53 -> 196.07603 | V53: =L53*$C53 -> 0 | W53: =M53*$C53 -> 17.478003 | X53: =N53*$C53 -> 86.053755 | Y53: =O53*$C53 -> 107.12814 | Z53: =P53*$C53 -> 0 | AA53: =Q53*$C53 -> 1.6500742 | ... AC53: =S53*$C53 -> 2.1060158 | AD53: Safran | AE53: FR | AF53: 18434.2 | AG53: 80
A54: Safran Electronics & Defense | B54: FR | C54: 1631.6 | E54: 2 | F54: =Ownership!D821/Ownership!D822 -> 0.2753897 | G54: =Ownership!E821/Ownership!E822 -> 0.57736713 | H54: =F54*C54 -> 449.32584 | I54: =G54*C54 -> 942.03221 | J54: =J$50 -> 0.095536136 | K54: =K$50 -> 0.2701516 | L54: =L$50 -> 0 | M54: =M$50 -> 0.024081019 | N54: =N$50 -> 0.11856401 | O54: =O$50 -> 0.14760008 | P54: =P$50 -> 0 | Q54: =Q$50 -> 0.0022734558 | ... S54: =S$50 -> 0.0029016476 | T54: =J54*$C54 -> 155.87676 | U54: =K54*$C54 -> 440.77935 | V54: =L54*$C54 -> 0 | W54: =M54*$C54 -> 39.29059 | X54: =N54*$C54 -> 193.44903 | Y54: =O54*$C54 -> 240.82428 | Z54: =P54*$C54 -> 0 | AA54: =Q54*$C54 -> 3.7093705 | ... AC54: =S54*$C54 -> 4.7343282 | AD54: Safran | AE54: FR | AF54: 18434.2 | AG54: 80
A55: Safran Engineering Services | B55: FR | D55: 161.9 | E55: 2 | F55: =Ownership!D821/Ownership!D822 -> 0.2753897 | G55: =Ownership!E821/Ownership!E822 -> 0.57736713 | H55: =F55*D55 -> 44.585593 | I55: =G55*D55 -> 93.475739 | J55: =J$50 -> 0.095536136 | K55: =K$50 -> 0.2701516 | L55: =L$50 -> 0 | M55: =M$50 -> 0.024081019 | N55: =N$50 -> 0.11856401 | O55: =O$50 -> 0.14760008 | P55: =P$50 -> 0 | Q55: =Q$50 -> 0.0022734558 | ... S55: =S$50 -> 0.0029016476 | T55: =J55*$D55 -> 15.4673 | U55: =K55*$D55 -> 43.737544 | V55: =L55*$D55 -> 0 | W55: =M55*$D55 -> 3.8987169 | X55: =N55*$D55 -> 19.195513 | Y55: =O55*$D55 -> 23.896452 | Z55: =P55*$D55 -> 0 | AA55: =Q55*$D55 -> 0.3680725 | ... AC55: =S55*$D55 -> 0.46977674 | AD55: Safran | AE55: FR | AF55: 18434.2 | AG55: 80
A56: Safran Filtration Systems | B56: FR | D56: 32.9 | E56: 2 | F56: =Ownership!D821/Ownership!D822 -> 0.2753897 | G56: =Ownership!E821/Ownership!E822 -> 0.57736713 | H56: =F56*D56 -> 9.0603212 | I56: =G56*D56 -> 18.995379 | J56: =J$50 -> 0.095536136 | K56: =K$50 -> 0.2701516 | L56: =L$50 -> 0 | M56: =M$50 -> 0.024081019 | N56: =N$50 -> 0.11856401 | O56: =O$50 -> 0.14760008 | P56: =P$50 -> 0 | Q56: =Q$50 -> 0.0022734558 | ... S56: =S$50 -> 0.0029016476 | T56: =J56*$D56 -> 3.1431389 | U56: =K56*$D56 -> 8.8879876 | V56: =L56*$D56 -> 0 | W56: =M56*$D56 -> 0.79226551 | X56: =N56*$D56 -> 3.9007558 | Y56: =O56*$D56 -> 4.8560425 | Z56: =P56*$D56 -> 0 | AA56: =Q56*$D56 -> 0.074796697 | ... AC56: =S56*$D56 -> 0.095464206 | AD56: Safran | AE56: FR | AF56: 18434.2 | AG56: 80
A57: Safran REOSC | B57: FR | C57: 43.6 | E57: 2 | F57: =Ownership!D821/Ownership!D822 -> 0.2753897 | G57: =Ownership!E821/Ownership!E822 -> 0.57736713 | H57: =F57*C57 -> 12.006991 | I57: =G57*C57 -> 25.173207 | J57: =J$50 -> 0.095536136 | K57: =K$50 -> 0.2701516 | L57: =L$50 -> 0 | M57: =M$50 -> 0.024081019 | N57: =N$50 -> 0.11856401 | O57: =O$50 -> 0.14760008 | P57: =P$50 -> 0 | Q57: =Q$50 -> 0.0022734558 | ... S57: =S$50 -> 0.0029016476 | T57: =J57*$C57 -> 4.1653755 | U57: =K57*$C57 -> 11.77861 | V57: =L57*$C57 -> 0 | W57: =M57*$C57 -> 1.0499324 | X57: =N57*$C57 -> 5.1693906 | Y57: =O57*$C57 -> 6.4353633 | Z57: =P57*$C57 -> 0 | AA57: =Q57*$C57 -> 0.099122675 | ... AC57: =S57*$C57 -> 0.12651183 | AD57: Safran | AE57: FR | AF57: 18434.2 | AG57: 80
A58: Sener Grupo de Ingenieria SA | B58: ES | C58: 474.3 | E58: 5 | F58: =Ownership!D511/Ownership!D512 -> 0 | G58: =Ownership!E511 -> 0 | H58: =F58*C58 -> 0 | I58: =G58*C58 -> 0 | J58: 0 | K58: 0 | L58: 0 | M58: 0 | N58: 0 | O58: 0 | P58: 0 | Q58: 0 | R58: 0 | S58: 0 | T58: =J58*$C58 -> 0 | U58: =K58*$C58 -> 0 | V58: =L58*$C58 -> 0 | W58: =M58*$C58 -> 0 | X58: =N58*$C58 -> 0 | Y58: =O58*$C58 -> 0 | Z58: =P58*$C58 -> 0 | AA58: =Q58*$C58 -> 0 | ... AC58: =S58*$C58 -> 0
A59: Sitael SPA | B59: IT | C59: 60.9 | E59: 2 | F59: =Ownership!D523/Ownership!D524 -> 0 | G59: =Ownership!E523 -> 0 | H59: =F59*C59 -> 0 | I59: =G59*C59 -> 0 | J59: 0 | K59: 0 | L59: 0 | M59: 0 | N59: 0 | O59: 0 | P59: 0 | Q59: 0 | R59: 0 | S59: 0 | T59: =J59*$C59 -> 0 | U59: =K59*$C59 -> 0 | V59: =L59*$C59 -> 0 | W59: =M59*$C59 -> 0 | X59: =N59*$C59 -> 0 | Y59: =O59*$C59 -> 0 | Z59: =P59*$C59 -> 0 | AA59: =Q59*$C59 -> 0 | ... AC59: =S59*$C59 -> 0 | AD59: mr Vito Pertosa
A60: SpaceAble | B60: FR | D60: 2 | E60: 1 | F60: =Ownership!D1028 -> 0 | G60: =Ownership!E1028/Ownership!E1029 -> 0 | H60: =F60*D60 -> 0 | I60: =G60*D60 -> 0 | J60: 0 | K60: 0 | L60: 0 | M60: 0 | N60: 0 | O60: 0 | P60: 0 | Q60: 0 | R60: 0 | S60: 0 | T60: =J60*$D60 -> 0 | U60: =K60*$D60 -> 0 | V60: =L60*$D60 -> 0 | W60: =M60*$D60 -> 0 | X60: =N60*$D60 -> 0 | Y60: =O60*$D60 -> 0 | Z60: =P60*$D60 -> 0 | AA60: =Q60*$D60 -> 0 | ... AC60: =S60*$D60 -> 0 | AD60: mr Julien Louis Andre Cantegreil | AE60: FR | AF60: - | AG60: -
A61: ST Engineering iDirect Europe CY NV | B61: BE | E61: - | H61: =F61*C61 -> 0 | I61: =G61*C61 -> 0 | J61: 0 | K61: 0 | L61: 0 | M61: 0 | N61: 0 | O61: 0 | P61: 0 | Q61: 0 | R61: 0 | S61: 0 | T61: =J61*$C61 -> 0 | U61: =K61*$C61 -> 0 | V61: =L61*$C61 -> 0 | W61: =M61*$C61 -> 0 | X61: =N61*$C61 -> 0 | Y61: =O61*$C61 -> 0 | Z61: =P61*$C61 -> 0 | AA61: =Q61*$C61 -> 0 | ... AC61: =S61*$C61 -> 0
A62: Tecnalia Research & Innovation | B62: ES | C62: 126.4 | E62: 1 | H62: =F62*C62 -> 0 | I62: =G62*C62 -> 0 | J62: 0 | K62: 0 | L62: 0 | M62: 0 | N62: 0 | O62: 0 | P62: 0 | Q62: 0 | R62: 0 | S62: 0 | T62: =J62*$C62 -> 0 | U62: =K62*$C62 -> 0 | V62: =L62*$C62 -> 0 | W62: =M62*$C62 -> 0 | X62: =N62*$C62 -> 0 | Y62: =O62*$C62 -> 0 | Z62: =P62*$C62 -> 0 | AA62: =Q62*$C62 -> 0 | ... AC62: =S62*$C62 -> 0
A63: Telespazio Belgium SRL (Vitrociset) | B63: BE | D63: 55 | E63: 4 | F63: =Ownership!D594/Ownership!D595 -> 0.2596837 | G63: =Ownership!E594/Ownership!E595 -> 0.4490146 | H63: =F63*D63 -> 14.282604 | I63: =G63*D63 -> 24.695803 | J63: =Ownership!D589/Ownership!D595 -> 0.14852166 | K63: =Ownership!E589/Ownership!E595 -> 0.35688152 | L63: =Ownership!D590/Ownership!D595 -> 0 | M63: =Ownership!E590/Ownership!E595 -> 0 | N63: =Ownership!D591/Ownership!D595 -> 0.076323631 | O63: =Ownership!E591/Ownership!E595 -> 0.02564311 | P63: =Ownership!D592/Ownership!D595 -> 0 | Q63: =Ownership!E592/Ownership!E595 -> 0.0032521383 | R63: =Ownership!D593/Ownership!D595 -> 0.034838414 | S63: =Ownership!E593/Ownership!E595 -> 0.052196819 | T63: =J63*$D63 -> 8.1686913 | U63: =K63*$D63 -> 19.628484 | V63: =L63*$D63 -> 0 | W63: =M63*$D63 -> 0 | X63: =N63*$D63 -> 4.1977997 | Y63: =O63*$D63 -> 1.4103711 | Z63: =P63*$D63 -> 0 | AA63: =Q63*$D63 -> 0.17886761 | ... AC63: =S63*$D63 -> 2.8708251 | AD63: Leonardo SPA | AE63: IT | AF63: 16515.2 | AG63: 47
A64: Telespazio Germany GMBH | B64: DE | C64: 69.4 | E64: 3 | F64: =Ownership!D594/Ownership!D595 -> 0.2596837 | G64: =Ownership!E594/Ownership!E595 -> 0.4490146 | H64: =F64*C64 -> 18.022049 | I64: =G64*C64 -> 31.161613 | J64: =J$63 -> 0.14852166 | K64: =K$63 -> 0.35688152 | L64: =L$63 -> 0 | M64: =M$63 -> 0 | N64: =N$63 -> 0.076323631 | O64: =O$63 -> 0.02564311 | P64: =P$63 -> 0 | Q64: =Q$63 -> 0.0032521383 | ... S64: =S$63 -> 0.052196819 | T64: =J64*$C64 -> 10.307403 | U64: =K64*$C64 -> 24.767578 | V64: =L64*$C64 -> 0 | W64: =M64*$C64 -> 0 | X64: =N64*$C64 -> 5.29686 | Y64: =O64*$C64 -> 1.7796319 | Z64: =P64*$C64 -> 0 | AA64: =Q64*$C64 -> 0.2256984 | ... AC64: =S64*$C64 -> 3.6224593 | AD64: Leonardo SPA | AE64: IT | AF64: 16515.2 | AG64: 47
A65: Telespazio SPA | B65: IT | C65: 341.2 | E65: 2 | F65: =Ownership!D594/Ownership!D595 -> 0.2596837 | G65: =Ownership!E594/Ownership!E595 -> 0.4490146 | H65: =F65*C65 -> 88.60408 | I65: =G65*C65 -> 153.20378 | J65: =J$63 -> 0.14852166 | K65: =K$63 -> 0.35688152 | L65: =L$63 -> 0 | M65: =M$63 -> 0 | N65: =N$63 -> 0.076323631 | O65: =O$63 -> 0.02564311 | P65: =P$63 -> 0 | Q65: =Q$63 -> 0.0032521383 | ... S65: =S$63 -> 0.052196819 | T65: =J65*$C65 -> 50.67559 | U65: =K65*$C65 -> 121.76798 | V65: =L65*$C65 -> 0 | W65: =M65*$C65 -> 0 | X65: =N65*$C65 -> 26.041623 | Y65: =O65*$C65 -> 8.7494292 | Z65: =P65*$C65 -> 0 | AA65: =Q65*$C65 -> 1.1096296 | ... AC65: =S65*$C65 -> 17.809555 | AD65: Leonardo SPA | AE65: IT | AF65: 16515.2 | AG65: 47
A66: Terma A/S | B66: DK | C66: 331.9 | E66: 3 | F66: =Ownership!D604 -> 0 | G66: =Ownership!E604/Ownership!E605 -> 0 | H66: =F66*C66 -> 0 | I66: =G66*C66 -> 0 | J66: 0 | K66: 0 | L66: 0 | M66: 0 | N66: 0 | O66: 0 | P66: 0 | Q66: 0 | R66: 0 | S66: 0 | T66: =J66*$C66 -> 0 | U66: =K66*$C66 -> 0 | V66: =L66*$C66 -> 0 | W66: =M66*$C66 -> 0 | X66: =N66*$C66 -> 0 | Y66: =O66*$C66 -> 0 | Z66: =P66*$C66 -> 0 | AA66: =Q66*$C66 -> 0 | ... AC66: =S66*$C66 -> 0 | AD66: Thomas B. Thriges Fond Tuborg Nord | AE66: DK | AF66: - | AG66: 5
A67: TESAT Spacecom GMBH&Co.KG | B67: DE | C67: 368.7 | E67: 2 | F67: =Ownership!D84/Ownership!D85 -> 0.092754528 | G67: =Ownership!E84/Ownership!E85 -> 0.13841121 | H67: =F67*C67 -> 34.198595 | I67: =G67*C67 -> 51.032214 | J67: =Ownership!D79/Ownership!D85 -> 0.092754528 | K67: =Ownership!E79/Ownership!E85 -> 0.13841121 | L67: 0 | M67: 0 | N67: 0 | O67: 0 | P67: 0 | Q67: 0 | R67: 0 | S67: 0 | T67: =J67*$C67 -> 34.198595 | U67: =K67*$C67 -> 51.032214 | V67: =L67*$C67 -> 0 | W67: =M67*$C67 -> 0 | X67: =N67*$C67 -> 0 | Y67: =O67*$C67 -> 0 | Z67: =P67*$C67 -> 0 | AA67: =Q67*$C67 -> 0 | ... AC67: =S67*$C67 -> 0 | AD67: Airbus SE | AE67: NL | AF67: 63178.9 | AG67: 12
A68: Thales Alenia Space Belgium | B68: BE | C68: 139.6 | E68: 2 | F68: =Ownership!D177/Ownership!D178 -> 0 | G68: =Ownership!E177/Ownership!E178 -> 0.20733636 | H68: =F68*C68 -> 0 | I68: =G68*C68 -> 28.944156 | J68: 0 | K68: =Ownership!E172/Ownership!E178 -> 0.13822424 | L68: 0 | M68: =Ownership!E173/Ownership!E178 -> 0.026836089 | N68: 0 | O68: =Ownership!E174/Ownership!E178 -> 0.011641226 | P68: 0 | Q68: =Ownership!E175/Ownership!E178 -> 0.0031860197 | R68: 0 | S68: =Ownership!E176/Ownership!E178 -> 0.019361197 | T68: =J68*$C68 -> 0 | U68: =K68*$C68 -> 19.296104 | V68: =L68*$C68 -> 0 | W68: =M68*$C68 -> 3.7463181 | X68: =N68*$C68 -> 0 | Y68: =O68*$C68 -> 1.6251151 | Z68: =P68*$C68 -> 0 | AA68: =Q68*$C68 -> 0.44476836 | ... AC68: =S68*$C68 -> 2.7028231 | AD68: Thales | AE68: FR | AF68: 20679.6 | AG68: 57
A69: Thales Alenia Space Deutschland GMBH | B69: DE | E69: 1 | F69: =Ownership!D177/Ownership!D178 -> 0 | G69: =Ownership!E177/Ownership!E178 -> 0.20733636 | H69: =F69*C69 -> 0 | I69: =G69*C69 -> 0 | J69: =J$68 -> 0 | K69: =K$68 -> 0.13822424 | L69: =L$68 -> 0 | M69: =M$68 -> 0.026836089 | N69: =N$68 -> 0 | O69: =O$68 -> 0.011641226 | P69: =P$68 -> 0 | Q69: =Q$68 -> 0.0031860197 | ... S69: =S$68 -> 0.019361197 | T69: =J69*$C69 -> 0 | U69: =K69*$C69 -> 0 | V69: =L69*$C69 -> 0 | W69: =M69*$C69 -> 0 | X69: =N69*$C69 -> 0 | Y69: =O69*$C69 -> 0 | Z69: =P69*$C69 -> 0 | AA69: =Q69*$C69 -> 0 | ... AC69: =S69*$C69 -> 0 | AD69: Thales | AE69: FR | AF69: 20679.6 | AG69: 57
A70: Thales Alenia Space Espana SA | B70: ES | C70: 108.6 | E70: 2 | F70: =Ownership!D177/Ownership!D178 -> 0 | G70: =Ownership!E177/Ownership!E178 -> 0.20733636 | H70: =F70*C70 -> 0 | I70: =G70*C70 -> 22.516729 | J70: =J$68 -> 0 | K70: =K$68 -> 0.13822424 | L70: =L$68 -> 0 | M70: =M$68 -> 0.026836089 | N70: =N$68 -> 0 | O70: =O$68 -> 0.011641226 | P70: =P$68 -> 0 | Q70: =Q$68 -> 0.0031860197 | ... S70: =S$68 -> 0.019361197 | T70: =J70*$C70 -> 0 | U70: =K70*$C70 -> 15.011153 | V70: =L70*$C70 -> 0 | W70: =M70*$C70 -> 2.9143993 | X70: =N70*$C70 -> 0 | Y70: =O70*$C70 -> 1.2642371 | Z70: =P70*$C70 -> 0 | AA70: =Q70*$C70 -> 0.34600174 | ... AC70: =S70*$C70 -> 2.102626 | AD70: Thales | AE70: FR | AF70: 20679.6 | AG70: 57
A71: Thales Alenia Space France | B71: FR | C71: 1853.1 | E71: 2 | F71: =Ownership!D177/Ownership!D178 -> 0 | G71: =Ownership!E177/Ownership!E178 -> 0.20733636 | H71: =F71*C71 -> 0 | I71: =G71*C71 -> 384.21501 | J71: =J$68 -> 0 | K71: =K$68 -> 0.13822424 | L71: =L$68 -> 0 | M71: =M$68 -> 0.026836089 | N71: =N$68 -> 0 | O71: =O$68 -> 0.011641226 | P71: =P$68 -> 0 | Q71: =Q$68 -> 0.0031860197 | ... S71: =S$68 -> 0.019361197 | T71: =J71*$C71 -> 0 | U71: =K71*$C71 -> 256.14334 | V71: =L71*$C71 -> 0 | W71: =M71*$C71 -> 49.729957 | X71: =N71*$C71 -> 0 | Y71: =O71*$C71 -> 21.572356 | Z71: =P71*$C71 -> 0 | AA71: =Q71*$C71 -> 5.9040132 | ... AC71: =S71*$C71 -> 35.878234 | AD71: Thales | AE71: FR | AF71: 20679.6 | AG71: 57
A72: Thales Alenia Space Italia SPA | B72: IT | C72: 896.3 | E72: 2 | F72: =Ownership!D177/Ownership!D178 -> 0 | G72: =Ownership!E177/Ownership!E178 -> 0.20733636 | H72: =F72*C72 -> 0 | I72: =G72*C72 -> 185.83558 | J72: =J$68 -> 0 | K72: =K$68 -> 0.13822424 | L72: =L$68 -> 0 | M72: =M$68 -> 0.026836089 | N72: =N$68 -> 0 | O72: =O$68 -> 0.011641226 | P72: =P$68 -> 0 | Q72: =Q$68 -> 0.0031860197 | ... S72: =S$68 -> 0.019361197 | T72: =J72*$C72 -> 0 | U72: =K72*$C72 -> 123.89039 | V72: =L72*$C72 -> 0 | W72: =M72*$C72 -> 24.053187 | X72: =N72*$C72 -> 0 | Y72: =O72*$C72 -> 10.434031 | Z72: =P72*$C72 -> 0 | AA72: =Q72*$C72 -> 2.8556295 | ... AC72: =S72*$C72 -> 17.353441 | AD72: Thales | AE72: FR | AF72: 20679.6 | AG72: 57
A73: Thales Alenia Space Luxembourg | B73: LU | E73: 1 | F73: =Ownership!D177/Ownership!D178 -> 0 | G73: =Ownership!E177/Ownership!E178 -> 0.20733636 | H73: =F73*C73 -> 0 | I73: =G73*C73 -> 0 | J73: =J$68 -> 0 | K73: =K$68 -> 0.13822424 | L73: =L$68 -> 0 | M73: =M$68 -> 0.026836089 | N73: =N$68 -> 0 | O73: =O$68 -> 0.011641226 | P73: =P$68 -> 0 | Q73: =Q$68 -> 0.0031860197 | ... S73: =S$68 -> 0.019361197 | T73: =J73*$C73 -> 0 | U73: =K73*$C73 -> 0 | V73: =L73*$C73 -> 0 | W73: =M73*$C73 -> 0 | X73: =N73*$C73 -> 0 | Y73: =O73*$C73 -> 0 | Z73: =P73*$C73 -> 0 | AA73: =Q73*$C73 -> 0 | ... AC73: =S73*$C73 -> 0 | AD73: Thales | AE73: FR | AF73: 20679.6 | AG73: 57
A74: Thales Alenia Space Polska | B74: PL | C74: 0.8 | E74: 1 | F74: =Ownership!D177/Ownership!D178 -> 0 | G74: =Ownership!E177/Ownership!E178 -> 0.20733636 | H74: =F74*C74 -> 0 | I74: =G74*C74 -> 0.16586909 | J74: =J$68 -> 0 | K74: =K$68 -> 0.13822424 | L74: =L$68 -> 0 | M74: =M$68 -> 0.026836089 | N74: =N$68 -> 0 | O74: =O$68 -> 0.011641226 | P74: =P$68 -> 0 | Q74: =Q$68 -> 0.0031860197 | ... S74: =S$68 -> 0.019361197 | T74: =J74*$C74 -> 0 | U74: =K74*$C74 -> 0.11057939 | V74: =L74*$C74 -> 0 | W74: =M74*$C74 -> 0.021468872 | X74: =N74*$C74 -> 0 | Y74: =O74*$C74 -> 0.0093129808 | Z74: =P74*$C74 -> 0 | AA74: =Q74*$C74 -> 0.0025488158 | ... AC74: =S74*$C74 -> 0.015488958 | AD74: Thales | AE74: FR | AF74: 20679.6 | AG74: 57
A75: TNO Tech Transfer Holding BV | B75: NL | E75: 1 | H75: =F75*C75 -> 0 | I75: =G75*C75 -> 0 | J75: 0 | K75: 0 | L75: 0 | M75: 0 | N75: 0 | O75: 0 | P75: 0 | Q75: 0 | R75: 0 | S75: 0 | T75: =J75*$C75 -> 0 | U75: =K75*$C75 -> 0 | V75: =L75*$C75 -> 0 | W75: =M75*$C75 -> 0 | X75: =N75*$C75 -> 0 | Y75: =O75*$C75 -> 0 | Z75: =P75*$C75 -> 0 | AA75: =Q75*$C75 -> 0 | ... AC75: =S75*$C75 -> 0 | AD75: Nederlands Organisatie voor Toegepast-Natuurwetenschappelijk Onderzoek TNO | AE75: NL | AF75: 845,2 (2009) | AG75: n.a.
A76: TTTech Computertechnik AG | B76: AT | C76: 135.8 | E76: 11 | F76: =Ownership!D638/Ownership!D639 -> 0.20004847 | G76: =Ownership!E638/Ownership!E639 -> 0.54234495 | H76: =F76*C76 -> 27.166582 | I76: =G76*C76 -> 73.650445 | J76: 0 | K76: 0 | L76: 0 | M76: 0 | N76: 0 | O76: 0 | P76: =Ownership!D636/Ownership!D639 -> 0.20004847 | Q76: =Ownership!E636/Ownership!E639 -> 0.54234495 | R76: 0 | S76: 0 | T76: =J76*$C76 -> 0 | U76: =K76*$C76 -> 0 | V76: =L76*$C76 -> 0 | W76: =M76*$C76 -> 0 | X76: =N76*$C76 -> 0 | Y76: =O76*$C76 -> 0 | Z76: =P76*$C76 -> 27.166582 | AA76: =Q76*$C76 -> 73.650445 | ... AC76: =S76*$C76 -> 0
A77: Total | C77: =SUM(C2:C76) -> 27972.3 | D77: =SUM(D2:D76) -> 13301.7 | H77: =SUM(H2:H76) -> 3410.7608 | I77: =SUM(I2:I76) -> 11220.277 | T77: =SUM(T2:T76) -> 2424.7544 | U77: =SUM(U2:U76) -> 6781.1112 | V77: =SUM(V2:V76) -> 590.12911 | W77: =SUM(W2:W76) -> 850.32058 | X77: =SUM(X2:X76) -> 841.93993 | Y77: =SUM(Y2:Y76) -> 1121.3314 | Z77: =SUM(Z2:Z76) -> 27.166582 | AA77: =SUM(AA2:AA76) -> 433.46229 | ... AC77: =SUM(AC2:AC76) -> 625.70176
B79: Direct | C79: Indirect
A80: Total revenue | B80: =C77+D77 -> 41274
A81: Total weighted direct/indirect industry non-EU ownership | B81: =H77 -> 3410.7608 | C81: =I77 -> 11220.277
A82: Share of non-EU direct and indirect ownership in industry | B82: =B81/B80 -> 0.082637029 | C82: =C81/B80 -> 0.27184854
A84: US | B84: =T77/$B$80 -> 0.058747744 | C84: =U77/$B$80 -> 0.16429499
A85: CA | B85: =V77/$B$80 -> 0.014297842 | C85: =W77/$B$80 -> 0.020601846
A86: UK | B86: =X77/$B$80 -> 0.020398797 | C86: =Y77/$B$80 -> 0.027167985
A87: CH | B87: =Z77/$B$80 -> 0.00065820085 | C87: =AA77/$B$80 -> 0.010502067
A88: NO | B88: =AB77/$B$80 -> 0.0036685837 | C88: =AC77/$B$80 -> 0.015159707
B90: =B82-SUM(B84:B88) -> -0.015134137 | C90: =C82-SUM(C84:C88) -> 0.034121952

Sheet Ownership
A1: Institution | B1: Country | C1: Type | D1: Direct ownership | E1: Indirect ownership
A2: ArianeGroup Holding (owner of Eurockot/ArianeGroup SAS/ArianeGroup GMBH/Arianespace)
A3: Airbus Defence & Space Holding France SAS | B3: FR | C3: C | E3: 0.5
A4: Safran | B4: FR | C4: C | D4: 0.5
A5: Agence des Participations de l'Etat | B5: FR | C5: S | E5: =D4*17.76% -> 0.0888
A6: Personnel de Safran | B6: - | C6: M | E6: =D4*10.29% -> 0.05145
A7: Safran Investissements | B7: FR | C7: F | E7: =D4*8.98% -> 0.0449
A8: Actionnaires Individuels | B8: - | C8: D | E8: =D4*8% -> 0.04
A9: The Children's Investment Master Fund | B9: KY | C9: E | E9: =D4*6.25% -> 0.03125
A10: FCPE Safran Investissement | B10: - | C10: E | E10: =D4*5.73% -> 0.02865
A11: TCI Fund Management UK Limited | B11: UK | C11: E | E11: =D4*4.79% -> 0.02395
A12: HSBC Holdings PLC | B12: UK | C12: B | E12: =D4*3.16% -> 0.0158
A13: CNP Assurances | B13: FR | C13: A | E13: =D4*2.75% -> 0.01375
A14: FCPE Avenir Safran | B14: - | C14: E | E14: =D4*1.99% -> 0.00995
A15: Harris Associates LP | B15: US | C15: C | E15: =D4*1.96% -> 0.0098
A16: Egerton Capital UK LLP | B16: UK | C16: F | E16: =D4*1.94% -> 0.0097
A17: Tweedy Browne Co LLC | B17: US | C17: C | E17: =D4*1.61% -> 0.00805
A18: Meritage Investment Partners LLC | B18: US | C18: F | E18: =D4*1.06% -> 0.0053
A19: Wellington Management Company LLP | B19: US | C19: C | E19: =D4*1.06% -> 0.0053
A20: Amundi Asset Management | B20: FR | C20: C | E20: =D4*0.99% -> 0.00495
A21: Lone Pine Capital LLC | B21: US | C21: Y | E21: =D4*0.97% -> 0.00485
A22: Viking Global Investors LP | B22: US | C22: P | E22: =D4*0.97% -> 0.00485
A23: Peugeot 1810 | B23: FR | C23: C | E23: =D4*0.8% -> 0.004
A24: Fonds Strategique de Participations | B24: FR | C24: E | E24: =D4*0.75% -> 0.00375
A25: PSA ID | B25: FR | C25: C | E25: =D4*0.7% -> 0.0035
A26: Self Owned | B26: - | C26: H | E26: =D4*0.63% -> 0.00315
A27: Bridgewater Associates LP | B27: US | C27: F | E27: =D4*0.46% -> 0.0023
A28: Banque Fédérative du Crédit Mutuel | B28: FR | C28: B | E28: =D4*0.3% -> 0.0015
A29: Salaries | B29: - | C29: M | E29: =D4*0.27% -> 0.00135
A30: Talos Capital Designated Activity Company | B30: IE | C30: E | E30: =D4*0.26% -> 0.0013
A31: CIFF Capital UK LP | B31: UK | C31: C | E31: =D4*0.15% -> 0.00075
A32: Peugeot Invest Assets | B32: UK | C32: F | E32: =D4*0.1% -> 0.0005
A33: US | D33: 0 | E33: =SUM(E15,E17:E19,E21:E22,E27) -> 0.04045
A34: Canada | D34: 0 | E34: 0
A35: UK | D35: 0 | E35: =SUM(E11:E12,E16,E31:E32) -> 0.0507
A36: Switzerland | D36: 0 | E36: 0
A37: Norway | D37: 0 | E37: 0
A38: Non-EU ownership | D38: 0 | E38: =SUM(E9,E11:E12,E15:E19,E21:E22,E27,E31:E32) -> 0.1224
A39: Total | D39: =SUM(D3:D32) -> 0.5 | E39: =SUM(E3:E32) -> 0.9234
A41: Enpulsion gmbh
A42: mr Alexander Reissner | B42: AT | C42: I | D42: 0.5048
A43: STI Space Technology Investment gmbh | B43: AT | C43: F | D43: 0.3067
A44: ASP Holding gmbh | B44: AT | C44: C | E44: =D43*66.66% -> 0.20444622
A45: Tenere Invest AG | B45: LI | C45: F | E45: =D43*33.33% -> 0.10222311
A46: ASP Consulting Gesellschaft M.B.H. | B46: AT | C46: C | D46: 0.0758
A47: ASP Holding gmbh | B47: AT | C47: C | E47: =D46*100% -> 0.0758
A48: AMR Invest gmbh & CO KG | B48: AT | C48: C | D48: 0.0455
A49: mr Alenxander Reissner | B49: AT | C49: I | E49: =D48*94.69% -> 0.04308395
A50: mr Torsten Vogel | B50: AT | C50: I | E50: =D48*5.3% -> 0.0024115
A51: Fotec Forschungs- & Technologietransfer gmbh | B51: AT | C51: C | D51: 0.0377
A52: Fachhochschule Wiener Neustadt gmbh | B52: AT | C52: C | E52: =D51*100% -> 0.0377
A53: mr David Krejci | B53: AT | C53: I | D53: 0.0292
A54: US | D54: 0 | E54: 0
A55: Canada | D55: 0 | E55: 0
A56: UK | D56: 0 | E56: 0
A57: Switzerland | D57: 0 | E57: 0
A58: Norway | D58: 0 | E58: 0
A59: Non-EU ownership | D59: 0 | E59: 0
A60: Total | D60: =SUM(D42:D59) -> 0.9997 | E60: =SUM(E42:E53) -> 0.46566478
A62: Airbus SE (owner of Jena-Optronik/Airbus Defence & Space GMBH/Airbus Defence & Space SA/Airbus Defence & Space SAS/Airbus Netherlands BV/TESAT Spacecom GMBH & CO.KG)
A63: SOGEPA | B63: FR | C63: C | D63: 0.109
A64: Agence des Participations de l'Etat | B64: FR | C64: S | E64: =D63*100% -> 0.109
A65: Gesellschaft zur Beteiligungsverwaltung GZBV MBH & CO.KG | B65: DE | C65: C | D65: 0.108
A66: KFW Bankengruppe | B66: DE | C66: B | E66: =D65*90.9% -> 0.098172
A67: Galintis GMBH & CO.KG | B67: DE | C67: C | E67: =D65*9.09% -> 0.0098172
A68: Sociedad Estatal de Participaciones Industriales | B68: ES | C68: S | D68: 0.041
A69: Subsecretaria Caja Pagadora Alcala | B69: ES | C69: S | E69: =D68*50% -> 0.0205
A70: Blackrock INC | B70: US | C70: B | E70: 0.0361
A71: TCI Fund Management LTD | B71: - | C71: C | D71: 0.0302
A72: Europacific Growth Fund | B72: US | C72: E | D72: 0.0297
A73: Goldman Sachs Group INC | B73: US | C73: B | E73: 0.0021
A74: Self owned | B74: NL | C74: H | D74: 0.002
A75: Torreal Sociedad de Capital Riesgo SA | B75: ES | C75: E | D75: 0.0003
A76: Torreal SA | B76: ES | C76: P | E76: =D75*86.49% -> 0.00025947
A77: Nueva Compania de Inversiones SA | B77: ES | C77: F | E77: =D75*8.39% -> 2.517e-05
A78: Miralver SPI SL | B78: ES | C78: C | E78: =D75*5.12% -> 1.536e-05
A79: US | D79: =D72 -> 0.0297 | E79: =E70+E73 -> 0.0382
A80: Canada | D80: 0 | E80: 0
A81: UK | D81: 0 | E81: 0
A82: Switzerland | D82: 0 | E82: 0
A83: Norway | D83: 0 | E83: 0
A84: non-EU ownership | D84: =D72 -> 0.0297 | E84: =E70+E73 -> 0.0382
A85: Total | D85: =SUM(D63:D75) -> 0.3202 | E85: =SUM(E63:E78) -> 0.2759892
A87: OHB SE (owner of OHB Italia SPA)
A88: Familienpool Fuchs | B88: DE | C88: I | D88: 0.6972
A89: mr Mayrhofer Romana Fuchs | B89: DE | C89: I | D89: 0.0217
A90: mr Luca Raffaele Rodolfo Nicola Pesarini (via its funds) | B90: CH | C90: I | E90: 0.0067
A91: Dimensional Holdings INC. (via its funds) | B91: US | C91: C | E91: 0.006
A92: Devon Equity Management Limited (via its funds) | B92: UK | C92: C | E92: 0.0058
A93: Praude Asset Management Limited (via its funds) | B93: ML | C93: E | E93: 0.0058
A94: Investor AM (via its funds) | B94: BE | C94: F | E94: 0.0052
A95: Accor (via its funds) | B95: FR | C95: C | E95: 0.0037
A96: Allianz SE (via its funds) | B96: DE | C96: A | E96: 0.0027
A97: Self owned | B97: DE | C97: H | D97: 0.0025
A98: Mandarine Gestion (via its funds) | B98: FR | C98: F | E98: 0.0023
A99: Grossbotzl, Schmitz & Partner Vermogensverwaltersozietat (via its funds) | B99: DE | C99: C | E99: 0.002
A100: ABRDN PLC (via its funds) | B100: UK | C100: A | E100: 0.0015
A101: BlackRock INC (via its funds) | B101: US | C101: B | E101: 0.0014
A102: DJE Kapital AG (via its funds) | B102: DE | C102: F | E102: 0.0014
A103: Ehrke & Lubberstedt AG (via its funds) | B103: DE | C103: C | E103: 0.0011
...

Sheet M&A
A1: Case | B1: Country | C1: target company | D1: Country | E1: acquiring company | F1: Non-EU takeover of EU company
A2: M.53 | B2: US | C2: Havilland (Boeing company) | D2: FR/IT | E2: Aerospatiale/Alenia-Aeritalia e Selenia spa | F2: No
A3: M.178 | B3: SW | C3: Ericson Radar Electronics | D3: SW | E3: Saab-Scania Combitech AB | F3: No
A4: M.237 | B4: NL | C4: Fokker | D4: DE | E4: Daimler-Benz | F4: No
A5: M.877 | B5: US | C5: MDC | D5: US | E5: Boeing | F5: No
A6: M.1185
A7: M.1198 | B7: SW | C7: Saab AB | D7: UK/SW | E7: British Aerospace plc/Investor AB | F7: No
A8: M.1309 | B8: FR | C8: Matra Hautes Technologies/Aérospatiale SNI | D8: FR | E8: Etat Francais/Lagardère SCA | F8: No
A9: M.1438 | B9: US | C9: MES (part of GEC) | D9: UK | E9: British Aerospace plc | F9: No
A10: M.1601 | B10: US | C10: Honeywell | D10: US | E10: AlliedSignal | F10: No
A11: M.1786 | B11: FR | C11: Thomson-CSF (Thales) | D11: US | E11: General Electric company | F11: Yes (jv)
A12: M.1636 | B12: FR | C12: Astrium | D12: FR/DE | E12: Matra Marconi Space/DaimlerChrysler Aerospace AG | F12: No
A13: M.1745 | B13: NL | C13: EADS NV (Airbus) | D13: DE/FR/ES | E13: DaimlerChrysler AG/Lagardère SCA/French State/ Sociedad Estatal de Participaciones Industriales | F13: No
A14: M.1879 | B14: US | C14: Hughes Electronics Corporation | D14: US | E14: Boeing | F14: No
A15: M.2061 | B15: NL | C15: Airbus | D15: NL | E15: EADS NV | F15: No
A16: M.2168 | B16: FR | C16: Hurel-Dubois | D16: FR | E16: e SociÈtÈ Nationale díEtude et de Construction de Moteurs díAviation | F16: No
A17: M.2183 | B17: UK | C17: TI Group plc | D17: UK | E17: Smiths Industries plc | F17: No
A18: M.2437 | B18: JPN | C18: Toshiba | D18: JPN | E18: NEC | F18: No
... A33: M.5151 | B33: US | C33: Global Aeronautica LLC | D33: US/IT | E33: Boeing/Finmeccanica Group | F33: No
A34: M.5276 | B34: NL | C34: Airbus (Laupheim manufacturing site) | E34: Diehl Stiftung & Co.KG/Thales SA | F34: No
A35: M.5357 | B35: NL | C35: Airbus SAS | D35: UK | E35: GKN plc | F35: No
A36: M.5168 | B36: UK | C36: Surrey Satellite Technology Limited | D36: NL | E36: EADS | F36: No
A37: M.5426 | B37: FR | C37: Thales | D37: FR | E37: Dassault Aviation | F37: No
A38: M.5667 | B38: CA | C38: Mecachrome International Inc. | D38: FR/CA | E38: ACE Management/Fonds de solidarité des travailleurs du Québec/ la Caisse des Dépôts et Consignations
A39: M.5668 | B39: FR | C39: Safran | D39: Singapore | E39: Singapore Airlines Limited | F39: Yes
A40: M.6581 | B40: SW | C40: Volvo Aero | D40: UK | E40: GKN plc | F40: No
A41: M.6844 | B41: IT | C41: Avio spa | D41: US | E41: General Electric company | F41: Yes
A42: M.7144 | B42: ES | C42: Synergy Industry and Technology, S.A. | D42: US | E42: Apollo Group
A43: M.7353 | B43: NL | C43: Airbus | D43: FR | E43: Safran | F43: No (JV)
A44: M.7676 | B44: NL | C44: Fokker Technologies Group BV | D44: UK | E44: GKN plc | F44: No
A45: M.7724 | B45: FR | C45: Arianespace SA | D45: FR | E45: Airbus Safran Launchers/Safran | F45: No
A46: M.8425 | B46: FR | C46: Zodiac Aerospace | D46: FR | E46: Safran | F46: No
A47: M.8688 | B47: US | C47: Orbital ATK | D47: US | E47: Northrop Grumman | F47: No
A48: M.8814 | B48: UK | C48: GKN plc | D48: UK | E48: Molrose Industries plc | F48: No
A49: M.8858 | B49: FR | C49: Safran | D49: US | E49: Boeing | F49: Yes (jv)
A50: M.8658 | B50: US | C50: Rockwell Collins | D50: US | E50: United Technologies Corporation | F50: No
A51: M.10506 | B51: UK | C51: Meggitt | D51: US | E51: Parker-Hannifin Corporation | F51: No

Sheet Tenders
A1: tender_id | B1: tender_publications_firstdContractAwardDate | C1: tender_publications_lastContractAwardDate | D1: lot_status | E1: lot_contractSignatureDate | F1: lot_cancellationDate | G1: tender_year | H1: tender_title | I1: tender_country | J1: bidder_country | K1: price | L1: bidder_name | M1: buyer_name | N1: buyer_buyerType | O1: bid_price_EUR | P1: tender_finalPrice_EUR | Q1: tender_estimatedPrice_EUR
A2: 89f99677-96a9-4021-a712-b4f58762b84f | B2: 42345 | C2: 42345 | D2: AWARDED | E2: 42346 | G2: 2015 | H2: Inel etansare 5125A-287-2 | I2: RO | J2: RO | K2: 194.48 | L2: AEROSTAR S.A. | M2: Unitatea Militara nr. 01969 -Campia Turzii | N2: NATIONAL_AGENCY | O2: 194.48
A3: ce946a21-3a23-4bb8-9392-87387eab2568 | B3: 43447 | C3: 43447 | D3: AWARDED | E3: 43447 | G3: 2018 | H3: Distantier CTP-placa flexibila | I3: RO | J3: RO | K3: 199.67 | L3: AEROTEH S.A. | M3: Unitatea Militara nr. 01969 -Campia Turzii | N3: NATIONAL_AGENCY | O3: 199.67
A4: 6fec0eb8-6f48-4340-bea2-227227dd71d3 | B4: 41586 | C4: 41586 | D4: AWARDED | E4: 41589 | G4: 2013 | H4: Elementi de filtrare filtru ulei CTP | I4: RO | J4: RO | K4: 800 | L4: AEROTEH S.A. | M4: Unitatea Militara nr. 01969 -Campia Turzii | N4: NATIONAL_AGENCY | O4: 800
A5: 9e085539-41dd-406d-ad3e-d89d4251da7a | B5: 42549 | C5: 42549 | D5: AWARDED | E5: 42550 | G5: 2016 | H5: Inel etansare 0257725 | I5: RO | J5: RO | L5: AEROSTAR S.A. | M5: Unitatea Militara nr. 01969 -Campia Turzii | N5: NATIONAL_AGENCY
A6: c8001d91-d725-4a02-928a-374f5f2d5ff0 | B6: 41787 | C6: 41787 | D6: AWARDED | E6: 41788 | G6: 2014 | H6: INEL DE ETANSARE EXTERIOR CAPAC FILTRU HIDRAULIC REPER FG11SN-1 - 212010 | I6: RO | J6: RO | L6: AEROSTAR S.A. | M6: Unitatea Militara nr. 01969 -Campia Turzii | N6: NATIONAL_AGENCY
A7: 40a6f028-c7bd-487b-be59-d443dc4f7811 | B7: 42549 | C7: 42549 | D7: AWARDED | E7: 42550 | G7: 2016 | H7: Conducta 76-5513-10-28 | I7: RO | J7: RO | K7: 497.97 | L7: AEROSTAR S.A. | M7: Unitatea Militara nr. 01969 -Campia Turzii | N7: NATIONAL_AGENCY | O7: 497.97
A8: 285151ec-71c5-4036-ae66-4377926f5196 | B8: 42639 | C8: 42639 | D8: AWARDED | E8: 42639 | G8: 2016 | H8: Masca de oxigen pilot MBU 12/P | I8: RO | J8: RO | K8: 343665 | L8: AEROFINA S.A. | M8: Ministerul Apararii U.M. 02512Z | N8: NATIONAL_AUTHORITY | O8: 343665
A9: 089604f0-00e9-4d0a-88b2-0d9b248294b6 | B9: 43746 | C9: 43746 | D9: AWARDED | E9: 43747 | G9: 2019 | H9: GARNITURA ASL 94-6402-161 GARNITURA ASL 74-0200-1005 | I9: RO | J9: RO | K9: 1024.66 | L9: AEROSTAR | M9: Ministerul Apararii Nationale - U.M.01912 BORCEA | O9: 1024.66
A10: 76735d79-2043-4585-8abf-08cb6bf73bda | B10: 41787 | C10: 41787 | D10: AWARDED | E10: 41788 | G10: 2014 | H10: INEL DE ETANSARE CORP-PAHAR FILTRU HIDRAULIC REPER 11GF4SN-1 - 212003 | I10: RO | J10: RO | K10: 179.38 | L10: AEROSTAR S.A. | M10: Unitatea Militara nr. 01969 -Campia Turzii | N10: NATIONAL_AGENCY | O10: 179.38
A11: bf85813a-49ec-4a21-a9d7-0b98b15c8024 | B11: 42345 | C11: 42345 | D11: AWARDED | E11: 42346 | G11: 2015 | H11: Inel etansare 74-0200-1008 | I11: RO | J11: RO | K11: 234.52 | L11: AEROSTAR S.A. | M11: Unitatea Militara nr. 01969 -Campia Turzii | N11: NATIONAL_AGENCY | O11: 234.52
A12: bbcae0aa-d56e-4709-b7df-c7631783356d | B12: 42550 | C12: 42550 | D12: AWARDED | E12: 42550 | G12: 2016 | H12: Punte de metalizare cu 3 papuci 200N1-1/12/12-90/180 | I12: RO | J12: RO | L12: AEROSTAR S.A. | M12: Unitatea Militara nr. 01969 -Campia Turzii | N12: NATIONAL_AGENCY
A13: 07918b92-1e4c-42eb-8c97-8a520449417e | B13: 41586 | C13: 41586 | D13: AWARDED | E13: 41586 | G13: 2013 | H13: Piulite cu autosigurantare | I13: RO | J13: RO | K13: 300.06 | L13: AEROTEH S.A. | M13: Unitatea Militara nr. 01969 -Campia Turzii | N13: NATIONAL_AGENCY | O13: 300.06
A14: c2546e65-3177-4278-a4b8-99eb021b719f | B14: 44118 | C14: 44118 | D14: AWARDED | E14: 44118 | G14: 2020 | H14: Racord gofrat 1655001 si Furtun IU27-15K | I14: RO | J14: RO | K14: 839.07 | L14: AEROSTAR | M14: Ministerul Apararii Nationale - U.M.01912 BORCEA | O14: 839.07
A15: 375d3e0d-91ce-4332-bf47-41a9063452d2 | B15: 42453 | C15: 42453 | D15: AWARDED | E15: 42453 | G15: 2016 | H15: Inel etansare OD87-30-4S | I15: RO | J15: RO | K15: 404.56 | L15: AEROSTAR S.A. | M15: Ministerul Apararii Nationale - U.M.01912 BORCEA | O15: 404.56
A16: 10fb0c4f-f83f-4242-92f5-fbba43efbce9 | B16: 42549 | C16: 42549 | D16: AWARDED | E16: 42550 | G16: 2016 | H16: Conducta E6U-5511-6030-654 | I16: RO | J16: RO | K16: 444.14 | L16: AEROSTAR S.A. | M16: Unitatea Militara nr. 01969 -Campia Turzii | N16: NATIONAL_AGENCY | O16: 444.14
A17: 2a3f935c-caea-4bc7-a26c-5989cbd7f28a | B17: 42345 | C17: 42345 | D17: AWARDED | E17: 42346 | G17: 2015 | H17: Conducta flexibila 76-5511-10-730 | I17: RO | J17: RO | K17: 1129.27 | L17: AEROSTAR S.A. | M17: Unitatea Militara nr. 01969 -Campia Turzii | N17: NATIONAL_AGENCY | O17: 1129.27
A18: e1276443-2058-4985-a8b8-c0490ade4e14 | B18: 42345 | C18: 42345 | D18: AWARDED | E18: 42346 | G18: 2015 | H18: Garnitura 2263A-10-1 | I18: RO | J18: RO | K18: 233.44 | L18: AEROSTAR S.A. | M18: Unitatea Militara nr. 01969 -Campia Turzii | N18: NATIONAL_AGENCY | O18: 233.44
A19: 9ca24181-ab80-4b1d-8a08-d370978851f9 | B19: 43026 | C19: 43026 | D19: AWARDED | E19: 43026 | G19: 2017 | H19: Sarma de sigurantat rezistenta la temperaturi inalte Ø0.5 mm | I19: RO | J19: RO | K19: 503.57 | L19: AEROSTAR S.A. | M19: Ministerul Apararii Nationale - U.M.01912 BORCEA | O19: 503.57
A20: 273dddb5-d310-4c0c-b6e5-4aa7cb0c1f35 | B20: 43447 | C20: 43447 | D20: AWARDED | E20: 43447 | G20: 2018 | H20: Burduf platou PRP reper 330A31-3243-00 | I20: RO | J20: RO | K20: 826.63 | L20: AEROTEH S.A. | M20: Unitatea Militara nr. 01969 -Campia Turzii | N20: NATIONAL_AGENCY | O20: 826.63
A21: bdde1e97-685e-4eeb-8506-4354b363eda6 | B21: 42143 | C21: 42143 | D21: AWARDED | E21: 42143 | G21: 2015 | H21: SPLINT INOX 2 X 40 | I21: RO | J21: RO | L21: AEROSTAR S.A. | M21: Ministerul Apararii Nationale - U.M.01912 BORCEA
A22: d4086308-29ed-44a0-8a99-aeec49bfab9a | B22: 43852 | C22: 43852 | D22: AWARDED | E22: 43857 | G22: 2020 | H22: Reparatie Modul Sursa de Alimentare, Model SPXL-750Q-P | I22: RO | J22: RO | K22: 9376 | L22: AEROSTAR | M22: Unitatea Militara 01812 | N22: NATIONAL_AUTHORITY | O22: 9376
A23: 912386ba-d0d7-46b0-b3b7-40e5a9cd8802 | B23: 42549 | C23: 42549 | D23: AWARDED | E23: 42550 | G23: 2016 | H23: Supapa 695020 | I23: RO | J23: RO | K23: 524.36 | L23: AEROSTAR S.A. | M23: Unitatea Militara nr. 01969 -Campia Turzii | N23: NATIONAL_AGENCY | O23: 524.36
A24: 0b32dd0d-ec76-4eb9-910d-972d9738a744 | B24: 42345 | C24: 42345 | D24: AWARDED | E24: 42346 | G24: 2015 | H24: Inel etansare 74-0200-1005 | I24: RO | J24: RO | K24: 333.19 | L24: AEROSTAR S.A. | M24: Unitatea Militara nr. 01969 -Campia Turzii | N24: NATIONAL_AGENCY | O24: 333.19
A25: 7b6b563a-5cfc-4e6b-b8a8-5fa6ebce7e10 | B25: 42549 | C25: 42549 | D25: AWARDED | E25: 42550 | G25: 2016 | H25: Saiba opritoare KT-102-18 | I25: RO | J25: RO | K25: 581.8 | L25: AEROSTAR S.A. | M25: Unitatea Militara nr. 01969 -Campia Turzii | N25: NATIONAL_AGENCY | O25: 581.8
A26: b30836a7-2236-4c3c-b3a0-83781c02f53d | B26: 41787 | C26: 41787 | D26: AWARDED | E26: 41788 | G26: 2014 | H26: INEL DE ETANSARE CAPAC FILTRU HIDRAULIC REPER 11GF4SN-1 - 212002 | I26: RO | J26: RO | L26: AEROSTAR S.A. | M26: Unitatea Militara nr. 01969 -Campia Turzii | N26: NATIONAL_AGENCY
A27: 6990823f-063b-46f9-a376-54c8357ec92b | B27: 42550 | C27: 42550 | D27: AWARDED | E27: 42550 | G27: 2016 | H27: Punte de metalizare cu 2 papuci 200N2-12/14-120 | I27: RO | J27: RO | L27: AEROSTAR S.A. | M27: Unitatea Militara nr. 01969 -Campia Turzii | N27: NATIONAL_AGENCY
A28: 5fba905f-0ad2-40af-b044-3b6122da4782 | B28: 42550 | C28: 42550 | D28: AWARDED | E28: 42550 | G28: 2016 | H28: Punte de metalizare cu 3 papuci 200N1-1-120/120 | I28: RO | J28: RO | L28: AEROSTAR S.A. | M28: Unitatea Militara nr. 01969 -Campia Turzii | N28: NATIONAL_AGENCY
A29: c64d8b93-8a1e-4604-960a-e4a55f54544c | B29: 42453 | C29: 42453 | D29: AWARDED | E29: 42453 | G29: 2016 | H29: Splint 3.2x50 DIN94 A2 | I29: RO | J29: RO | L29: AEROSTAR S.A. | M29: Ministerul Apararii Nationale - U.M.01912 BORCEA
A30: 79ea3bf2-06a4-4cc5-9703-da5cea33eb2a | B30: 43614 | C30: 43614 | D30: AWARDED | E30: 43614 | G30: 2019 | H30: Caseta DTC , reper AO 02582A-00 | I30: RO | J30: RO | K30: 1238905 | L30: AEROSTAR | M30: Ministerul Apararii Nationale - U.M.01912 BORCEA | O30: 1238905
A31: ced98527-e805-436b-82b9-65d708f131f6 | B31: 42613 | C31: 42613 | D31: AWARDED | E31: 42613 | G31: 2016 | H31: Conducta flexibila 94-9511-570/A | I31: RO | J31: RO | K31: 131336 | L31: AEROSTAR S.A. | M31: Ministerul Apararii Nationale - U.M.01912 BORCEA | O31: 131336
A32: 4fcd7ca8-d6d6-4a2a-bfec-ac2389629a06 | B32: 42639 | C32: 42639 | D32: AWARDED | E32: 42639 | G32: 2016 | H32: Casca pilot HGU 55/P | I32: RO | J32: RO | K32: -24653 | L32: AEROFINA S.A. | M32: Ministerul Apararii U.M. 02512Z | N32: NATIONAL_AUTHORITY | O32: 1832.7
A33: 2b38aa63-b826-49b0-aa76-280aa1310154 | B33: 43788 | C33: 43788 | D33: AWARDED | E33: 43788 | G33: 2019 | H33: Diafragma 76-5505-592 | I33: RO | J33: RO | K33: -7090 | L33: AEROSTAR | M33: Ministerul Apararii Nationale - U.M.01912 BORCEA | O33: 1880.08
A34: 36adcabd-4e98-4808-9480-744ed4166a7f | B34: 43773 | C34: 43773 | D34: AWARDED | E34: 43773 | G34: 2019 | H34: AX SUSPENSIE S52.64.218 | I34: RO | J34: RO | K34: 651.93 | L34: AEROSTAR | M34: Ministerul Apararii Nationale - U. M. 02015 Bacau | N34: NATIONAL_AUTHORITY | O34: 651.93
A35: 271fee60-c7dc-480e-9a32-139654e6c41d | B35: 42549 | C35: 42549 | D35: AWARDED | E35: 42550 | G35: 2016 | H35: Inel etansare 0257107 | I35: RO | J35: RO | K35: 389.66 | L35: AEROSTAR S.A. | M35: Unitatea Militara nr. 01969 -Campia Turzii | N35: NATIONAL_AGENCY | O35: 389.66
A36: a20fabf1-b8c3-405f-8f69-178d7df64b63 | B36: 41254 | C36: 41254 | D36: AWARDED | E36: 41255 | G36: 2012 | H36: Casca pilot tip HGU-55/P, marca GENTEX, marime medie, culoare gri. | I36: RO | J36: RO | K36: 1775.51 | L36: AEROFINA S.A. | M36: Ministerul Apararii U.M. 02512Z | N36: NATIONAL_AUTHORITY | O36: 1775.51
A37: b0c0d5d7-9ba9-45f7-80c2-6fcad6ffa0a1 | B37: 42345 | C37: 42345 | D37: AWARDED | E37: 42346 | G37: 2015 | H37: Conducta 94-5512-10-56 | I37: RO | J37: RO | K37: 511.9 | L37: AEROSTAR S.A. | M37: Unitatea Militara nr. 01969 -Campia Turzii | N37: NATIONAL_AGENCY | O37: 511.9
A38: ee62be08-8bf2-4292-94cb-9b42220c1581 | B38: 42345 | C38: 42345 | D38: AWARDED | E38: 42346 | G38: 2015 | H38: Garnitura 4327-155N607-33,4-5,4-2 | I38: RO | J38: RO | L38: AEROSTAR S.A. | M38: Unitatea Militara nr. 01969 -Campia Turzii | N38: NATIONAL_AGENCY
A39: d004200e-27d7-4061-9697-2fb911e8d802 | B39: 43893 | C39: 43893 | D39: AWARDED | E39: 43894 | G39: 2020 | H39: Conducte flexibile reper 76-5511-1890-2 94-5511-570A Kit etansare PS 870 B1/2 | I39: RO | J39: RO | K39: 4298.78 | L39: AEROSTAR | M39: Ministerul Apararii Nationale - U.M.01912 BORCEA | O39: 4298.78
A40: dfe7e178-7a8c-4d05-8e5d-ad6ba1beb494 | B40: 42345 | C40: 42345 | D40: AWARDED | E40: 42346 | G40: 2015 | H40: Inel etansare 2262a-222-2 | I40: RO | J40: RO | L40: AEROSTAR S.A. | M40: Unitatea Militara nr. 01969 -Campia Turzii | N40: NATIONAL_AGENCY
A41: 14e97bf1-ca30-4bf6-9f32-0acafd6e7f56 | B41: 41787 | C41: 41787 | D41: AWARDED | E41: 41788 | G41: 2014 | H41: GARNITURI CAUCIUC LEGATURA REZ. PLAN "Y" - 4327-155N607-33.4-5.4-2 | I41: RO | J41: RO | L41: AEROSTAR S.A. | M41: Unitatea Militara nr. 01969 -Campia Turzii | N41: NATIONAL_AGENCY
A42: 81a5a2ea-8da3-4c38-81e7-2bb22aba7f2b | B42: 42550 | C42: 42550 | D42: AWARDED | E42: 42550 | G42: 2016 | H42: Punte de metalizare cu 3 papuci 200N1-1/1/12-80/120 | I42: RO | J42: RO | L42: AEROSTAR S.A. | M42: Unitatea Militara nr. 01969 -Campia Turzii | N42: NATIONAL_AGENCY
A43: 6129a920-5765-4ab4-8fd9-f2ddca454961 | B43: 42549 | C43: 42549 | D43: AWARDED | E43: 42550 | G43: 2016 | H43: Inel etansare 155N607-11.6-3.25 | I43: RO | J43: RO | L43: AEROSTAR S.A. | M43: Unitatea Militara nr. 01969 -Campia Turzii | N43: NATIONAL_AGENCY
A44: 0bb243a0-9a9e-41e5-ab4d-3f74f16e041c | B44: 42453 | C44: 42453 | D44: AWARDED | E44: 42453 | G44: 2016 | H44: Inel etansare 2263A18-1 | I44: RO | J44: RO | K44: 397.03 | L44: AEROSTAR S.A. | M44: Ministerul Apararii Nationale - U.M.01912 BORCEA | O44: 397.03
A45: 21b8265a-69f2-4d9f-9380-122d112e08f7 | B45: 42671 | C45: 42671 | D45: AWARDED | E45: 42671 | G45: 2016 | H45: Inel etansare 74-0200-1005 | I45: RO | J45: RO | K45: 360.82 | L45: AEROSTAR S.A. | M45: Ministerul Apararii Nationale - U.M.01912 BORCEA | O45: 360.82
A46: 5191928c-94eb-4c2f-a6e1-62a2979b6939 | B46: 42677 | C46: 42677 | D46: AWARDED | E46: 42681 | G46: 2016 | H46: 330A34-4132-20] Vizor | I46: RO | J46: RO | K46: 251.79 | L46: AEROTEH S.A. | M46: Unitatea Militara nr. 01969 -Campia Turzii | N46: NATIONAL_AGENCY | O46: 251.79
A47: 528f405a-aee0-4574-aab4-b7b2290c8d5f | B47: 43734 | C47: 43734 | D47: AWARDED | E47: 43734 | G47: 2019 | H47: Sarma zincata ∅ 0.5, ∅ 0.8 | I47: RO | J47: RO | K47: 624.8 | L47: AEROSTAR | M47: Ministerul Apararii Nationale - U.M.01912 BORCEA | O47: 624.8
A48: 8747dc74-ba80-4a04-ab63-4e25cc64c7e2 | B48: 42549 | C48: 42549 | D48: AWARDED | E48: 42550 | G48: 2016 | H48: Inel 2609S52-11-1.5-1078 | I48: RO | J48: RO | L48: AEROSTAR S.A. | M48: Unitatea Militara nr. 01969 -Campia Turzii | N48: NATIONAL_AGENCY
A49: 3d3e94e0-ab11-4d74-bd2d-708f314073a1 | B49: 42549 | C49: 42549 | D49: AWARDED | E49: 42550 | G49: 2016 | H49: Conducta 94-5511-20-160 | I49: RO | J49: RO | K49: 591.5 | L49: AEROSTAR S.A. | M49: Unitatea Militara nr. 01969 -Campia Turzii | N49: NATIONAL_AGENCY | O49: 591.5
A50: 1489fb2e-3b61-461f-98d6-3ab8a44d42fa | B50: 41787 | C50: 41787 | D50: AWARDED | E50: 41788 | G50: 2014 | H50: INEL DE ETANSARE CORP-PAHAR FILTRUHIDRAULIC REPER 74-5505-580 - 76-5505-546-13 | I50: RO | J50: RO | L50: AEROSTAR S.A. | M50: Unitatea Militara nr. 01969 -Campia Turzii | N50: NATIONAL_AGENCY
A51: d9ffe97a-267d-4f2d-ba47-5d5c38c1d900 | B51: 42345 | C51: 42345 | D51: AWARDED | E51: 42346 | G51: 2015 | H51: Inel etansare 155N607-25.6-3.25 | I51: RO | J51: RO | L51: AEROSTAR S.A. | M51: Unitatea Militara nr. 01969 -Campia Turzii | N51: NATIONAL_AGENCY
A52: 8286ffe3-1ce6-441b-9724-7cc914a0c5cd | B52: 42230 | C52: 42230 | D52: AWARDED | E52: 42230 | G52: 2015 | H52: GARNITURI ASL 94-6402-161 | I52: RO | J52: RO | K52: 659.06 | L52: AEROSTAR S.A. | M52: Ministerul Apararii Nationale - U.M.01912 BORCEA | O52: 659.06
A53: 576eb1db-f956-47fb-9c66-9bc862c0aab7 | B53: 41787 | C53: 41787 | D53: AWARDED | E53: 41788 | G53: 2014 | H53: GARNITURA POMPA HIDRAULICA NP34M-1T - 9V-6100-9005 | I53: RO | J53: RO | L53: AEROSTAR S.A. | M53: Unitatea Militara nr. 01969 -Campia Turzii | N53: NATIONAL_AGENCY
A54: 04aec3fa-522c-464d-b7cc-3dcd03e7af7a | B54: 42025 | C54: 42025 | D54: AWARDED | E54: 42030 | G54: 2015 | H54: RULMENT SPATE LOGAN | I54: RO | J54: RO | L54: BLACSIR COM IMPEX SRL | M54: INSPECTORATUL JUDETEAN DE POLITIE BRAILA | N54: OTHER
A55: 95784449-63f2-4b43-86b5-02a398bc6703 | B55: 42550 | C55: 42550 | D55: AWARDED | E55: 42550 | G55: 2016 | H55: Punte de metalizare cu 3 papuci 200N1-1-90/100 | I55: RO | J55: RO | L55: AEROSTAR S.A. | M55: Unitatea Militara nr. 01969 -Campia Turzii | N55: NATIONAL_AGENCY
A56: e2b6edd7-059c-4b83-82a4-03b355f17abf | B56: 42677 | C56: 42677 | D56: AWARDED | E56: 42681 | G56: 2016 | H56: [330A31-3243-00] Burduf | I56: RO | J56: RO | K56: 287.76 | L56: AEROTEH S.A. | M56: Unitatea Militara nr. 01969 -Campia Turzii | N56: NATIONAL_AGENCY | O56: 287.76
A57: 35064d8b-f7ee-4f63-ad0f-4d68c0a07b01 | B57: 42550 | C57: 42550 | D57: AWARDED | E57: 42550 | G57: 2016 | H57: Punte de metalizare cu 2 papuci 200N2-12-80 | I57: RO | J57: RO | L57: AEROSTAR S.A. | M57: Unitatea Militara nr. 01969 -Campia Turzii | N57: NATIONAL_AGENCY
A58: ebc4c55c-8674-4294-a079-3c010925eabe | B58: 42639 | C58: 42639 | D58: AWARDED | E58: 42639 | G58: 2016 | H58: Casca pilot HGU 55/P | I58: RO | J58: RO | K58: -24653 | L58: AEROFINA S.A. | M58: Ministerul Apararii U.M. 02512Z | N58: NATIONAL_AUTHORITY | O58: 1832.7
A59: e27b2870-b9a2-4ea7-ae14-34f5ac1d43f1 | B59: 42549 | C59: 42549 | D59: AWARDED | E59: 42550 | G59: 2016 | H59: Conducta 94-5512-10-56 | I59: RO | J59: RO | K59: 552.53 | L59: AEROSTAR S.A. | M59: Unitatea Militara nr. 01969 -Campia Turzii | N59: NATIONAL_AGENCY | O59: 552.53
A60: 16cba237-b1c9-419a-9327-69a46996a219 | B60: 42346 | C60: 42346 | D60: AWARDED | E60: 42346 | G60: 2015 | H60: Inel etansare 201-7810-02 | I60: RO | J60: RO | L60: AEROSTAR S.A. | M60: Unitatea Militara nr. 01969 -Campia Turzii | N60: NATIONAL_AGENCY
A61: 7de153c8-c2a1-4f72-8278-8b0d24fa1fb2 | B61: 44068 | C61: 44068 | D61: AWARDED | E61: 44068 | G61: 2020 | H61: GARNITURA 94-6402-161 | I61: RO | J61: RO | K61: 367.73 | L61: AEROSTAR | M61: Unitatea Militara nr. 01969 -Campia Turzii | N61: NATIONAL_AGENCY | O61: 367.73
A62: 6228c777-0003-4cb9-8a76-2db77ee93580 | B62: 44068 | C62: 44068 | D62: AWARDED | E62: 44068 | G62: 2020 | H62: Inel etansare 3826-155N607-33.6-3.25 | I62: RO | J62: RO | K62: 154.29 | L62: AEROSTAR | M62: Unitatea Militara nr. 01969 -Campia Turzii | N62: NATIONAL_AGENCY | O62: 154.29
A63: 627e1363-3f74-4653-a351-41e405adedf4 | B63: 44068 | C63: 44068 | D63: AWARDED | E63: 44068 | G63: 2020 | H63: Inel etansare 2263A-18-1 | I63: RO | J63: RO | K63: 191.69 | L63: AEROSTAR | M63: Unitatea Militara nr. 01969 -Campia Turzii | N63: NATIONAL_AGENCY | O63: 191.69
A64: 7fe6b78a-a6d1-4a09-a5c1-79d2b4fc13d7 | B64: 44068 | C64: 44068 | D64: AWARDED | E64: 44068 | G64: 2020 | H64: Inel etansare 2263A-22-1 | I64: RO | J64: RO | K64: 192.29 | L64: AEROSTAR | M64: Unitatea Militara nr. 01969 -Campia Turzii | N64: NATIONAL_AGENCY | O64: 192.29
A65: 62ee1725-018a-4d77-b5a7-7ed55001c5ca | B65: 43956 | C65: 43956 | D65: AWARDED | E65: 43956 | G65: 2020 | H65: Reparatie transmisie cardan echipat din sistemul de rotire antena pentru radare terestre, gama metri | I65: RO | J65: RO | K65: 1942.67 | L65: AEROSTAR | M65: Unitatea Militara 01812 | N65: NATIONAL_AUTHORITY | O65: 1942.67
A66: a8afd953-4edd-4afd-a25b-434b1a387d98 | B66: 43577 | C66: 43577 | D66: AWARDED | E66: 43577 | G66: 2019 | H66: Molding compound E-400P | I66: RO | J66: RO | K66: 1918.34 | L66: AEROSTAR | M66: Ministerul Apararii Nationale - U.M.01912 BORCEA | O66: 1918.34
A67: 16691772-1b74-41f9-a875-a035eca636e0 | B67: 44147 | C67: 44147 | D67: AWARDED | E67: 44147 | G67: 2020 | H67: Casca GENTEX | I67: RO | J67: RO | K67: 3533.42 | L67: AEROFINA S.A. | M67: Ministerul Apararii Nationale, Unitatea Militara 02512 Z | N67: NATIONAL_AUTHORITY | O67: 3533.42
A68: d0bfb892-96e7-46ba-8c11-4abf4ae4c1ae | B68: 44068 | C68: 44068 | D68: AWARDED | E68: 44068 | G68: 2020 | H68: Inel etansare 2267A-165-2 | I68: RO | J68: RO | K68: 452.05 | L68: AEROSTAR | M68: Unitatea Militara nr. 01969 -Campia Turzii | N68: NATIONAL_AGENCY | O68: 452.05
A69: 97f4959f-f041-4a03-b2d7-493b9f20b8d2 | B69: 44068 | C69: 44068 | D69: AWARDED | E69: 44068 | G69: 2020 | H69: Inel etansare 76-4102-115 | I69: RO | J69: RO | L69: AEROSTAR | M69: Unitatea Militara nr. 01969 -Campia Turzii | N69: NATIONAL_AGENCY
A70: 9ba3e2a5-65ee-43ba-a8c3-a766ff4ff10f | B70: 42550 | C70: 42550 | D70: AWARDED | E70: 42550 | G70: 2016 | H70: Punte de metalizare cu 2 papuci 200N2-12/14-120 | I70: RO | J70: RO | L70: AEROSTAR S.A. | M70: Unitatea Militara nr. 01969 -Campia Turzii | N70: NATIONAL_AGENCY
A71: 5ae4073c-f867-4920-8c8d-3c89f4da2b99 | B71: 42384 | C71: 42384 | D71: AWARDED | E71: 42384 | G71: 2016 | H71: Splint inox 2x40 | I71: RO | J71: RO | L71: AEROSTAR S.A. | M71: Ministerul Apararii Nationale - U.M.01912 BORCEA
A72: 2ee007ab-65c1-4acf-8e3b-f5e168a5da43 | B72: 44068 | C72: 44068 | D72: AWARDED | E72: 44068 | G72: 2020 | H72: Inel etansare 3826-155N607-17.6-3.25 | I72: RO | J72: RO | K72: 148.51 | L72: AEROSTAR | M72: Unitatea Militara nr. 01969 -Campia Turzii | N72: NATIONAL_AGENCY | O72: 148.51
A73: 02af0a6a-dc17-459d-91ef-0869b049b53d | B73: 42549 | C73: 42549 | D73: AWARDED | E73: 42550 | G73: 2016 | H73: Impingator 695007M | I73: RO | J73: RO | L73: AEROSTAR S.A. | M73: Unitatea Militara nr. 01969 -Campia Turzii | N73: NATIONAL_AGENCY
A74: ce6717c1-d215-4b67-86e3-d998ad2d0302 | B74: 44068 | C74: 44068 | D74: AWARDED | E74: 44068 | G74: 2020 | H74: INEL ETANSARE 2263A-20-1 | I74: RO | J74: RO | K74: 191.69 | L74: AEROSTAR | M74: Unitatea Militara nr. 01969 -Campia Turzii | N74: NATIONAL_AGENCY | O74: 191.69
A75: ce711344-d97c-44ea-b986-8956161f6d47 | B75: 42549 | C75: 42549 | D75: AWARDED | E75: 42550 | G75: 2016 | H75: Inel etansare 155N607-37.5-4-2 | I75: RO | J75: RO | K75: 224.3 | L75: AEROSTAR S.A. | M75: Unitatea Militara nr. 01969 -Campia Turzii | N75: NATIONAL_AGENCY | O75: 224.3
A76: 92818344-c9cd-4d11-8376-55c313d6d7c7 | B76: 42550 | C76: 42550 | D76: AWARDED | E76: 42550 | G76: 2016 | H76: Punte de metalizare cu 3 papuci 200N1-12-120/140 | I76: RO | J76: RO | L76: AEROSTAR S.A. | M76: Unitatea Militara nr. 01969 -Campia Turzii | N76: NATIONAL_AGENCY
A77: 6838aad3-383c-4274-a3db-f7daa37d4ffc | B77: 42549 | C77: 42549 | D77: AWARDED | E77: 42550 | G77: 2016 | H77: Siguranta 0240010 | I77: RO | J77: RO | L77: AEROSTAR S.A. | M77: Unitatea Militara nr. 01969 -Campia Turzii | N77: NATIONAL_AGENCY
A78: 93c4b5a5-bd5e-45fa-8156-1e00010d8933 | B78: 42550 | C78: 42550 | D78: AWARDED | E78: 42550 | G78: 2016 | H78: Metalizarea 6245C56-2-140 | I78: RO | J78: RO | L78: AEROSTAR S.A. | M78: Unitatea Militara nr. 01969 -Campia Turzii | N78: NATIONAL_AGENCY
A79: 9783e8ad-00a8-42d7-b835-cfa99b7a76b6 | B79: 42550 | C79: 42550 | D79: AWARDED | E79: 42550 | G79: 2016 | H79: Punte de metalizare cu 2 papuci 200N2-1-90 | I79: RO | J79: RO | L79: AEROSTAR S.A. | M79: Unitatea Militara nr. 01969 -Campia Turzii | N79: NATIONAL_AGENCY
A80: 6d93d2ef-3a19-4c05-929c-49d526df8ee8 | B80: 42934 | C80: 42934 | D80: AWARDED | E80: 42934 | G80: 2017 | H80: Sarma zincata Ø0.8 mm | I80: RO | J80: RO | K80: 109.04 | L80: AEROSTAR S.A. | M80: Ministerul Apararii Nationale - U.M.01912 BORCEA | O80: 109.04
A81: 2e39cf4b-0654-4c0d-ac9a-4353671f2787 | B81: 42345 | C81: 42345 | D81: AWARDED | E81: 42346 | G81: 2015 | H81: Conducta flexibila 76-5512-960S | I81: RO | J81: RO | K81: 362.52 | L81: AEROSTAR S.A. | M81: Unitatea Militara nr. 01969 -Campia Turzii | N81: NATIONAL_AGENCY | O81: 362.52
A82: 45495963-237e-463b-9c89-349c6ea7b040 | B82: 43523 | C82: 43523 | D82: AWARDED | E82: 43524 | G82: 2019 | H82: Piese de echipament aerospatial militar | I82: RO | J82: RO | K82: 15480.97 | L82: AEROSTAR | M82: Unitatea Militara nr. 01969 -Campia Turzii | N82: NATIONAL_AGENCY | O82: 15480.97
A83: 271d920c-5931-4a0b-ada7-3846650c99c5 | B83: 41787 | C83: 41787 | D83: AWARDED | E83: 41788 | G83: 2014 | H83: INEL DE ETANSARE INTERIOR CAPAC FILTRU HIDRAULIC REPER FG11SN-1 - 212009 | I83: RO | J83: RO | L83: AEROSTAR S.A. | M83: Unitatea Militara nr. 01969 -Campia Turzii | N83: NATIONAL_AGENCY
A84: 61bdc50d-eb60-4632-bb12-6eab5e5ab107 | B84: 42345 | C84: 42345 | D84: AWARDED | E84: 42346 | G84: 2015 | H84: Inel etansare 2609s52-11-1,5-1078 | I84: RO | J84: RO | L84: AEROSTAR S.A. | M84: Unitatea Militara nr. 01969 -Campia Turzii | N84: NATIONAL_AGENCY
A85: f90727ce-87d3-4d23-9de1-0cf7713307fd | B85: 42384 | C85: 42384 | D85: AWARDED | E85: 42384 | G85: 2016 | H85: Splint inox 1.2x20 | I85: RO | J85: RO | L85: AEROSTAR S.A. | M85: Ministerul Apararii Nationale - U.M.01912 BORCEA
A86: eb0d5223-33e9-4753-b013-895ac648427b | B86: 42550 | C86: 42550 | D86: AWARDED | E86: 42550 | G86: 2016 | H86: Punte de metalizare cu 2 papuci 200N2-12-100 | I86: RO | J86: RO | L86: AEROSTAR S.A. | M86: Unitatea Militara nr. 01969 -Campia Turzii | N86: NATIONAL_AGENCY
A87: 68dd1c2d-ec44-413b-b440-bf39d46ab9ee | B87: 43277 | C87: 43277 | D87: AWARDED | E87: 43277 | G87: 2018 | H87: Sarma zincata Ф0.5mm | I87: RO | J87: RO | L87: AEROSTAR | M87: Ministerul Apararii Nationale - U.M.01912 BORCEA
A88: f47090f6-3a4c-4a97-b534-7d9256c8ddbc | B88: 42550 | C88: 42550 | D88: AWARDED | E88: 42550 | G88: 2016 | H88: Punte de metalizare cu 2 papuci 200N1-1-100/90 | I88: RO | J88: RO | L88: AEROSTAR S.A. | M88: Unitatea Militara nr. 01969 -Campia Turzii | N88: NATIONAL_AGENCY
A89: b2e2a26a-3eda-462a-9045-a139bbee3b7f | B89: 42550 | C89: 42550 | D89: AWARDED | E89: 42550 | G89: 2016 | H89: Punte de metalizare cu 2 papuci 200N2-12-120 | I89: RO | J89: RO | L89: AEROSTAR S.A. | M89: Unitatea Militara nr. 01969 -Campia Turzii | N89: NATIONAL_AGENCY
A90: 7717de46-de9f-4b75-933c-c157dc056ec3 | B90: 42550 | C90: 42550 | D90: AWARDED | E90: 42550 | G90: 2016 | H90: Punte de metalizare cu 2 papuci 200N2-1-90 | I90: RO | J90: RO | L90: AEROSTAR S.A. | M90: Unitatea Militara nr. 01969 -Campia Turzii | N90: NATIONAL_AGENCY
A91: 4e3ea985-3810-4498-8c13-bf6b7cd0d5f7 | B91: 42453 | C91: 42453 | D91: AWARDED | E91: 42453 | G91: 2016 | H91: Inel etansare OD87-32.5-4S | I91: RO | J91: RO | K91: 406.44 | L91: AEROSTAR S.A. | M91: Ministerul Apararii Nationale - U.M.01912 BORCEA | O91: 406.44
A92: 78e86474-8f63-4c0d-b7d5-5e7bc81e664e | B92: 42549 | C92: 42549 | D92: AWARDED | E92: 42550 | G92: 2016 | H92: Garnitura 94-6402-161 | I92: RO | J92: RO | K92: 398.28 | L92: AEROSTAR S.A. | M92: Unitatea Militara nr. 01969 -Campia Turzii | N92: NATIONAL_AGENCY | O92: 398.28
A93: 851773a8-a4b1-4c2c-8713-4b0d078676ff | B93: 43651 | C93: 43651 | D93: AWARDED | E93: 43651 | G93: 2019 | H93: Ansamblu cablu suspendat sistem franare aeronave BAK-12 SMART ARREST | I93: RO | J93: RO | K93: 14606.27 | L93: BUSINESS PLUS | M93: Ministerul Apararii Nationale - U.M.01912 BORCEA | O93: 14606.27
A94: 63dcf45b-d4a2-4503-b5c3-f7cb0dc7fca2 | B94: 43747 | C94: 43747 | D94: AWARDED | E94: 43747 | G94: 2019 | H94: BULON PRINDERE CORP JAMBA SEMIFURCA F52-64-218 (DREAPTA) | I94: RO | J94: RO | K94: 1305.67 | L94: AEROSTAR | M94: Ministerul Apararii Nationale - U. M. 02015 Bacau | N94: NATIONAL_AUTHORITY | O94: 1305.67
A95: c383559e-adda-42a4-89d4-00593d626ec5 | B95: 43710 | C95: 43710 | D95: AWARDED | G95: 2019 | H95: Filtru ulei hidraulic + garnitura pentru sistem franare BAK-12 | I95: RO | J95: RO | K95: 401981 | L95: S.C. ARIES COMERT & INDUSTRIE S.R.L. | M95: Ministerul Apararii Nationale - U.M.01912 BORCEA | P95: 401981 | Q95: 401981
A96: f934d8e1-3d52-4622-8a95-5c6e84a22bd9 | B96: 42550 | C96: 42550 | D96: AWARDED | E96: 42550 | G96: 2016 | H96: Punte de metalizare cu 2 papuci 200N2-12-120 | I96: RO | J96: RO | L96: AEROSTAR S.A. | M96: Unitatea Militara nr. 01969 -Campia Turzii | N96: NATIONAL_AGENCY
A97: 7e34764a-8725-4b02-bbb7-e1a0fc7e10bb | B97: 42346 | C97: 42346 | D97: AWARDED | E97: 42346 | G97: 2015 | H97: Garnitura OD87-15-2.6J/N | I97: RO | J97: RO | K97: 231.88 | L97: AEROSTAR S.A. | M97: Unitatea Militara nr. 01969 -Campia Turzii | N97: NATIONAL_AGENCY | O97: 231.88
A98: 3eed5578-4fb8-4036-b501-11ec840531e6 | B98: 41787 | C98: 41787 | D98: AWARDED | E98: 41788 | G98: 2014 | H98: GARNITURI CAUCIUC LEGATURA REZ. PLAN "Y" - 4327-155N607-61-5.5-2 | I98: RO | J98: RO | L98: AEROSTAR S.A. | M98: Unitatea Militara nr. 01969 -Campia Turzii | N98: NATIONAL_AGENCY
A99: c0ad7cb7-060f-4822-91ad-c8eb70f796c8 | B99: 42549 | C99: 42549 | D99: AWARDED | E99: 42550 | G99: 2016 | H99: Inel etansare 4327 155N607-33.4-5.4-2 | I99: RO | J99: RO | L99: AEROSTAR S.A. | M99: Unitatea Militara nr. 01969 -Campia Turzii | N99: NATIONAL_AGENCY
A100: 4d4c533d-a618-4a0a-ac5c-625e2883b9b9 | B100: 41079 | C100: 41079 | D100: AWARDED | E100: 41075 | G100: 2012 | H100: Piese de schimb pentru echipamentele produse de ROHDE SCHWARZ | I100: RO | J100: RO | K100: 115176 | L100: ROHDE & SCHWARZ ROMANIA S.R.L. | M100: R.A. ROMATSA - ADMINISTRATIA ROMANA A SERVICIILOR DE TRAFIC AERIAN | N100: OTHER | O100: 115176 | P100: 115065
...

Sheet Copernicus
A1: Copernicus contracts (> 15 000 euro)
A2: Country | B2: 2014 | C2: 2015 | D2: 2016 | E2: 2017 | F2: 2018 | G2: 2019 | H2: 2020 | I2: 2021 | J2: 2022 | K2: #contracts | L2: % non EU contracts
A3: UK | B3: - | C3: - | D3: - | E3: - | F3: - | G3: - | H3: =COUNTIF('2020'!B2:B155,A3) -> 4 | I3: =COUNTIF('2021'!B2:B224,A3) -> 6 | J3: =COUNTIF('2022'!B2:B334,A3) -> 5 | K3: =SUM(H3:J3) -> 15 | L3: =K3/K9 -> 0.011709602
A4: NO | B4: =COUNTIF('2014'!B:B,Copernicus!A4) -> 1 | C4: =COUNTIF('2015'!B:B,A4) -> 6 | D4: =COUNTIF('2016'!B:B,A4) -> 2 | E4: =COUNTIF('2017'!B:B,A4) -> 1 | F4: =COUNTIF('2018'!B:B,A4) -> 0 | G4: =COUNTIF('2019'!B:B,A4) -> 2 | H4: =COUNTIF('2020'!B:B,A4) -> 1 | I4: =COUNTIF('2021'!B:B,A4) -> 5 | J4: =COUNTIF('2022'!B:B,A4) -> 4 | K4: =SUM(B4:J4) -> 22 | L4: =K4/K9 -> 0.017174083
A5: CH | B5: =COUNTIF('2014'!B:B,A5) -> 0 | C5: =COUNTIF('2015'!B:B,A5) -> 10 | D5: =COUNTIF('2016'!B:B,A5) -> 4 | E5: =COUNTIF('2017'!B:B,A5) -> 3 | F5: =COUNTIF('2018'!B:B,A5) -> 1 | G5: =COUNTIF('2019'!B:B,A5) -> 2 | H5: =COUNTIF('2020'!B:B,A5) -> 0 | I5: =COUNTIF('2021'!B:B,A5) -> 2 | J5: =COUNTIF('2022'!B:B,A5) -> 0 | K5: =SUM(B5:J5) -> 22 | L5: =K5/K9 -> 0.017174083
A6: US | B6: =COUNTIF('2014'!B:B,Copernicus!A6) -> 0 | C6: =COUNTIF('2015'!B:B,Copernicus!A6) -> 1 | D6: =COUNTIF('2016'!B:B,Copernicus!A6) -> 0 | E6: =COUNTIF('2017'!B:B,Copernicus!A6) -> 0 | F6: =COUNTIF('2018'!B:B,Copernicus!A6) -> 0 | G6: =COUNTIF('2019'!B:B,Copernicus!A6) -> 0 | H6: =COUNTIF('2020'!B:B,Copernicus!A6) -> 0 | I6: =COUNTIF('2021'!B:B,Copernicus!A6) -> 0 | J6: =COUNTIF('2022'!B:B,Copernicus!A6) -> 1 | K6: =SUM(B6:J6) -> 2 | L6: =K6/K9 -> 0.0015612802
A7: CA | B7: =COUNTIF('2014'!B:B,Copernicus!A7) -> 0 | C7: =COUNTIF('2015'!B:B,Copernicus!A7) -> 2 | D7: =COUNTIF('2016'!B:B,Copernicus!A7) -> 1 | E7: =COUNTIF('2017'!B:B,Copernicus!A7) -> 1 | F7: =COUNTIF('2018'!B:B,Copernicus!A7) -> 0 | G7: =COUNTIF('2019'!B:B,Copernicus!A7) -> 2 | H7: =COUNTIF('2020'!B:B,Copernicus!A7) -> 1 | I7: =COUNTIF('2021'!B:B,Copernicus!A7) -> 4 | J7: =COUNTIF('2022'!B:B,Copernicus!A7) -> 1 | K7: =SUM(B7:J7) -> 12 | L7: =K7/K9 -> 0.0093676815
A8: Total non EU contracts | B8: =SUM(B4:B7) -> 1 | C8: =SUM(C4:C7) -> 19 | D8: =SUM(D4:D7) -> 7 | E8: =SUM(E4:E7) -> 5 | F8: =SUM(F4:F7) -> 1 | G8: =SUM(G4:G7) -> 6 | H8: =SUM(H3:H7) -> 6 | I8: =SUM(I3:I7) -> 17 | J8: =SUM(J3:J7) -> 11 | K8: =SUM(B8:J8) -> 73 | L8: =K8/K9 -> 0.056986729
A9: Total #contracts | B9: =COUNTA('2014'!B:B)-1 -> 6 | C9: =COUNTA('2015'!B:B)-1 -> 189 | D9: =COUNTA('2016'!B:B)-1 -> 115 | E9: =COUNTA('2017'!B:B)-1 -> 86 | F9: =COUNTA('2018'!B:B)-1 -> 81 | G9: =COUNTA('2019'!B:B)-1 -> 94 | H9: =COUNTA('2020'!B:B)-1 -> 154 | I9: =COUNTA('2021'!B:B)-1 -> 223 | J9: =COUNTA('2022'!B:B)-1 -> 333 | K9: =SUM(B9:J9) -> 1281
A11: Copernicus Sentinels industrial consortium
A12: Country | B12: Sentinel 1 | C12: Sentinel 2 | D12: Sentinel 3 | E12: Sentinel 4 | F12: Sentinel 5 | G12: #components | H12: % non EU components
A13: NO | B13: =COUNTIF('Sentinel 1'!C:C,Copernicus!A13) -> 1 | C13: =COUNTIF('Sentinel 2'!C:C,Copernicus!A13) -> 0 | D13: =COUNTIF('Sentinel 3'!C:C,Copernicus!A13) -> 2 | E13: =COUNTIF('Sentinel 4'!C:C,Copernicus!A13) -> 2 | F13: =COUNTIF('Sentinel 5'!C:C,Copernicus!A13) -> 0 | G13: =SUM(B13:F13) -> 5 | H13: =G13/G19 -> 0.013812155
A14: CH | B14: =COUNTIF('Sentinel 1'!C:C,Copernicus!A14) -> 9 | C14: =COUNTIF('Sentinel 2'!C:C,Copernicus!A14) -> 2 | D14: =COUNTIF('Sentinel 3'!C:C,Copernicus!A14) -> 7 | E14: =COUNTIF('Sentinel 4'!C:C,Copernicus!A14) -> 3 | F14: =COUNTIF('Sentinel 5'!C:C,Copernicus!A14) -> 3 | G14: =SUM(B14:F14) -> 24 | H14: =G14/G19 -> 0.066298343
A15: US | B15: =COUNTIF('Sentinel 1'!C:C,Copernicus!A15) -> 1 | C15: =COUNTIF('Sentinel 2'!C:C,Copernicus!A15) -> 2 | D15: =COUNTIF('Sentinel 3'!C:C,Copernicus!A15) -> 0 | E15: =COUNTIF('Sentinel 4'!C:C,Copernicus!A15) -> 0 | F15: =COUNTIF('Sentinel 5'!C:C,Copernicus!A15) -> 0 | G15: =SUM(B15:F15) -> 3 | H15: =G15/G19 -> 0.0082872928
A16: CA | B16: =COUNTIF('Sentinel 1'!C:C,Copernicus!A16) -> 1 | C16: =COUNTIF('Sentinel 2'!C:C,Copernicus!A16) -> 1 | D16: =COUNTIF('Sentinel 3'!C:C,Copernicus!A16) -> 2 | E16: =COUNTIF('Sentinel 4'!C:C,Copernicus!A16) -> 0 | F16: =COUNTIF('Sentinel 5'!C:C,Copernicus!A16) -> 0 | G16: =SUM(B16:F16) -> 4 | H16: =G16/G19 -> 0.011049724
A17: IL | B17: =COUNTIF('Sentinel 1'!C:C,Copernicus!A17) -> 3 | C17: =COUNTIF('Sentinel 2'!C:C,Copernicus!A17) -> 0 | D17: =COUNTIF('Sentinel 3'!C:C,Copernicus!A17) -> 1 | E17: =COUNTIF('Sentinel 4'!C:C,Copernicus!A17) -> 0 | F17: =COUNTIF('Sentinel 5'!C:C,Copernicus!A17) -> 0 | G17: =SUM(B17:F17) -> 4 | H17: =G17/G19 -> 0.011049724
A18: Total non EU components | B18: =SUM(B13:B17) -> 15 | C18: =SUM(C13:C17) -> 5 | D18: =SUM(D13:D17) -> 12 | E18: =SUM(E13:E17) -> 5 | F18: =SUM(F13:F17) -> 3 | G18: =SUM(B18:F18) -> 40 | H18: =G18/G19 -> 0.11049724
A19: Total #components | B19: =COUNTA('Sentinel 1'!C:C)-1 -> 81 | C19: =COUNTA('Sentinel 2'!C:C)-1 -> 38 | D19: =COUNTA('Sentinel 3'!C:C)-1 -> 136 | E19: =COUNTA('Sentinel 4'!C:C)-1 -> 57 | F19: =COUNTA('Sentinel 5'!C:C)-1 -> 50 | G19: =SUM(B19:F19) -> 362

Sheet Sentinel 1
A1: Component | B1: Supplier | C1: Country
A2: GPS | B2: RUAG (Austria) | C2: AT
A3: TCS | B3: RUAG (Austria) | C3: AT
A4: PCDU | B4: TAS-Etca (Belgium) | C4: BE
A5: Basic products | B5: MDA (Canada) | C5: CA
A6: STR | B6: RUAG (Switzerland) | C6: CH
A7: STR | B7: Apco (Switzerland) | C7: CH
A8: End-to-end SAR system calibration | B8: DLR (Germany) | C8: DE
A9: FSS | B9: Jena-Optronik (Germany) | C9: DE
A10: RW | B10: Rockwell C (Germany) | C10: DE
A11: SAW | B11: Astrium (Germany) | C11: DE
A12: PVF | B12: Astrium (Germany) | C12: DE
... A82: Test equipment | B82: SSBV (Netherlands) | C82: NL

Sheet Sentinel 2
A1: Component | B1: Supplier | C1: Country
A2: GPS receiver | B2: RUAG (Austria) | C2: AT
A3: Electrical Ground Support Equipment (EGSE) | B3: Siemens (Austria) | C3: AT
A4: Mirror polishing | B4: AMSO (Belgium) | C4: BE
A5: MGSE | B5: Sermati (Canada) | C5: CA
A6: Solar Array Drive Mechanism | B6: RUAG (Switzerland) | C6: CH
A7: Mechanical Ground Support Equipment (MGSE) for the instrument primary and secondary structure and the satellites | B7: APCO (Switzerland), | C7: CH
A8: Satellites Platform procurement and AIT, mass memory, Coarse Earth and Sun Sensors, propulsion | B8: Prime Contractor: Astrium GmbH (Germany) | C8: DE
A9: Star sensors, Video and Compression Unit, optical filters | B9: Jena-Optronik (Germany) | C9: DE
A10: Star sensors, Video and Compression Unit, optical filters | B10: Optics Balzers Jena (Germany) | C10: DE
A11: Magnetometers and magnetorquers | B11: ZARM (Germany) | C11: DE
A12: Mechanical Ground Support Equipment (MGSE) for the instrument primary and secondary structure and the satellites | B12: Xperion (Germany) | C12: DE
... A39: Miniature Inertial Measurement Unit | B39: Honeywell (USA) | C39: US

Sheet Sentinel 3
A1: Component | B1: Supplier | C1: Country
A2: MGSE | B2: AMOS (Belgium) | C2: BE
A3: AOCS engineering support | B3: NCG (Canada) | C3: CA
A4: O-SPS scene generator | B4: Vista (Germany) | C4: DE
A5: PA software | B5: ETIQ (Germany) | C5: DE
A6: Mission analysis | B6: Deimos (Spain) | C6: ES
A7: Support to PA activities | B7: Alter (Spain) | C7: ES
A8: Support to PA activities | B8: Thales Alenia Space España (Spain) | C8: ES
A9: CPPA | B9: Alter (Spain) | C9: ES
A10: O-GPP | B10: Deimos (Spain) | C10: ES
A11: SRAL GPP | B11: Isardsat (Spain) | C11: ES
A12: GPS GPP & SPS | B12: GMV (Spain) | C12: ES
... A25: AOCS SCOE | B25: Studiel UK (UK) | C25: UK
A26: Schedule/documentation/configuration | B26: VEGA
A27: Platform Prime Contractor/System Engineering Support | B27: Thales Alenia Space (Italy) | C27: IT
A28: Battery | B28: ABSL (UK) | C28: UK
A29: PDHU | B29: Astrium GmbH (Germany) | C29: DE
A30: PCDU | B30: Thales Alenia Space ETCA (Belgium) | C30: BE
A31: Structure | B31: RUAG (Switzerland) | C31: CH
A32: TXA | B32: Thales Alenia Space España (Spain) | C32: ES
A33: SBT | B33: Thales Alenia Space España (Spain) | C33: ES
A34: Thermal control | B34: EADS Casa Espacio (Spain) | C34: ES
A35: SADM | B35: Kongsberg (Norway) | C35: NO
A36: Solar Array Wings | B36: Thales Alenia Space (France) | C36: FR
A37: SBA | B37: RUAG (Sweden) | C37: SW
A38: XBAA | B38: Thales Alenia Space (Italy) | C38: IT
... A138: VCF VEM Support to validation | B138: Skysoft (Portugal) | C138: PT

Sheet Sentinel 4
A1: Component | B1: Supplier | C1: Country
A2: (AIT) OGSE | B2: MICOS | C2: CH
A3: (AIT) OGSE | B3: Optek | C3: IT
A4: (AIT) OGSE | B4: NPL | C4: UK
A5: Aperature Cover | B5: RUAG | C5: AT
A6: Aperature Cover | B6: Active Space | C6: PT
A7: Beam Splitter Assy. | B7: JOP | C7: DE
A8: Beam Splitter Assy. | B8: IOF | C8: DE
A9: Beam Splitter Assy. | B9: Sagem | C9: FR
A10: C&C Facilities | B10: STFC | C10: UK
A11: C&C Facilities | B11: RAL | C11: UK
A12: C&C OGSE | B12: UCLC | C12: UK
... A58: UV/VIS Spectrometer Optics Assy. | B58: JOP | C58: DE

Sheet Sentinel 5
A1: Component | B1: Supplier | C1: Country
A2: IOMT | B2: RUAG | C2: AT
A3: EGSE | B3: ATOS | C3: AT
A4: C&C OGSE SM, test support, E2E verification | B4: CSL | C4: BE
A5: Structure | B5: Almatech | C5: CH
A6: CAS | B6: Micos | C6: CH
A7: MGSE | B7: APCO | C7: CH
A8: Prime contractor | B8: Airbus Defence and Space GMBH | C8: DE
A9: CFRP panels | B9: Xperion | C9: DE
A10: Heat pipes | B10: Airbus DS GMBH | C10: DE
A11: Mechanical engineering & mech. MAIT | B11: STI | C11: DE
A12: NIR SO | B12: Jena Optronik | C12: DE
... A51: C&C Test facilities | B51: RAL | C51: UK

Sheet 2014
A1: Name of Recipient | B1: Country | C1: Summary of Activities | D1: Contract value
A2: ARIANESPACE S. A. | B2: FR | C2: PROVISION OF THE LAUNCH SERVICES FOR THE SENTINEL-2 PAYLOAD | D2: 6,825,700.00
A3: EUROCKOT LAUNCH SERVICES GMBH | B3: DE | C3: PROVISION OF THE LAUNCH SERVICES FOR THE SENTINEL-5P PAYLOAD | D3: 26,900,000.00
A4: e-GEOS SPA | B4: IT | C4: PREPARATION AND OPERATION OF THE CORE X-BAND ACQUISITION AND NEAR REAL-TIME FACILITIES FOR THE COPERNICUS SENTINEL SATELLITES: MATERA GROUND STATION | D4: 13,378,925.00
A5: KONGSBERG SATELLITE SERVICES AS (KSAT) | B5: NO | C5: PREPARATION AND OPERATION OF THE CORE X-BAND ACQUISITION AND NEAR REAL-TIME FACILITIES FOR THE COPERNICUS SENTINEL SATELLITES: SVALBARD GROUND STATION | D5: 43,662,184.00
A6: Collecte Localisation Satellites (CLS) | B6: FR | C6: MISSION PERFORMANCE CENTERS (MPC) FOR SENTINEL 1A/B. MPCs are responsible for calibration, validation, quality control and end-to-end system performance assessment. The MPCs include expert teams for specific cal/val, off-line quality control and algorithm correction activities. | D6: 6,473,009.00
A7: T-SYSTEMS INTERNATIONAL GMBH | B7: DE | C7: DATA CIRCULATION & DISSEMINATION FOR THE WIDE AREA NETWORK (WAN) AND SECURITY SERVICES FOR THE COPERNICUS SENTINELS SATELLITES | D7: 16,072,707.21

Sheet 2015
A1: Name of Recipient | B1: Country | C1: Summary of Activities | D1: • Copernicus 2015
A2: ABSL SPACE PRODUCTS | B2: UK | C2: {Sentinel 1 Satellites C/D IJnits construction | D2: 3,038,000.00
A3: ABSL SPACE PRODUCTS | B3: UK | C3: Sentinel 2 Satellites C/D Units construction | D3: 997,000.00
A4: ABSL SPACE PRODUCTS | B4: UK | C4: (Sentinel 3 Satellite C/D Units Construction | D4: 1,049,735.00
A5: ACM-ST S.A.S. | B5: FR | C5: MISSION PERFORMANCE CENTERS (MPC) FOR SENTINELS. MPCs are responsible for calibration, :validation, quality control and end-to-end system performance assessment. The MPCs include expert teams for specific cal/val, off-line quality control and algorithm correction activities. | D5: 21,882,062.00
A6: ACRI-ST S.A.S. | B6: FR | C6: Preparations and operations of the off-line Processing and Archiving Centres for sentinel {satellites | D6: 7,745,656.00
A7: ACRI-ST S.A.S. | B7: FR | C7: (Sentinel 3 Payload Data Ground Segment (PDGS) system operations, maintenance and evolutions | D7: 24,513.00
A8: ACS ADVANCED COMPUTER SYSTEMS | B8: IT | C8: Sentinel 2 Payload Data Ground Segment (PDGS) system operations, maintenance and evolutions | D8: 229,145.00
A9: ADMATIS LTD | B9: HU | C9: 'Sentinel 2 Satellites C/D Units construction | D9: 609,810.00
A10: ADVANCED COMPUTER SYSTEMS SPA | B10: IT | C10: (Sentinel 3 Payload Data Ground Segment (PDGS) system operations, maintenance and evolutions | D10: 71,455.00
A11: AIM INFRAROT-MODULE GMBH | B11: DE | C11: Sentinel 3 Satellite C/D Units Construction | D11: 1,815,000.00
A12: AIRBUS OEFENCE SPACE NETHERLANDS | B12: NL | C12: Sentinel 1 Satellites C/D Units construction | D12: 5,750,000.00
... A35: ARE-SYS SRL | B35: IT | C35: {Sentinel 1B Phase E Activities | D35: 31,800.00
A36: ARIANESPACE | B36: FR | D36: 70,356,152.05
A37: ASTRIUM GMBH - SATELLITES | B37: DE | C37: DATA RELAY SERVICES FOR COPERNICUS SENTINELS (EDRS) | D37: 70,492,472.00
A38: ASTRIUV GMBH - SATELLITES | B38: DE | C38: (Sentinel 1 Satellites C/D Units construction | D38: 76,393,104.00
A39: ASTRIUV GMBH - SATELLITES | B39: DE | C39: Sentinel 1B Phase E Activities | D39: 546,8.89.00
A40: ASTRIUM GMBH - SATELLITES | B40: DE | C40: {Sentinel 2 Satellites C/D Units construction | D40: 101,702,188.00
A41: ASTRIUM GMBH - SATELLITES | B41: DE | C41: •Sentinel 2A Phase E Activities | D41: 6,388,000.00
A42: ASTRIUM GMBH - SATELLITES | B42: DE | C42: •Sentinel 3 Satellite C/D Units Construction | D42: 6,471,809.00
A43: ASTRIUM GMBH - SATELLITES | B43: DE | C43: Sentinel 5 Satellites- Recurrent Models B and C | D43: 81,261,548.00
A44: ASTRIUM GMBH - SATELLITES | B44: DE | C44: Sentinel 6B Satellite Instrument Construction | D44: 4,061,579.00
A45: AXON KABELGMBH | B45: DE | C45: •Sentinel 1 Satellites C/D Units construction | D45: 250,000.00
A46: Black8ridge AG | B46: DE | C46: •Copernicus Space Component - Data Warehouse activities | D46: 6,867,262.00
A47: BLU ELECTRONIC SRO | B47: IT | C47: Sentinel 1 Satellites C/D Units construction | D47: 800,000.00
A48: BOOSTEC | B48: FR | C48: {Sentinel 2 Satellites C/D Units construction | D48: 2,745,000.00
... A61: DA-DESIGN OY | B61: FI | C61: •Sentinel 1 Satellites C/D Units construction | D61: 4,100,000.00
A62: OEIMOS ENGENHARIA S.A. | B62: PT | D62: 108,040.00
A63: DEMOS IMAGING S.L.U. | B63: ES | C63: Copernicus Space Compon ent - Data Warehouse activities | D63: 18,969,686.00
A64: DEMOS SPACE S.L.U | B64: ES | C64: •Copernicus Space Compon ent - Data Warehouse activities | D64: 606,576.00
A65: DEMOS SPACE S.L.U | B65: ES | C65: :Sentinel 2 Payload Data Ground Segment (PDGS) system operations, maintenance and evolutions | D65: 215,935.00
A66: DLR - Germen Aerospace Center | B66: DE | C66: Copernicus Space Component - Data Warehouse activities | D66: 187,782.00
A67: DLR - Germen Aerospace Center | B67: DE | C67: • DLR CALIBRATION SUPPORT for S-IA Routine ops | D67: 499,995.00
A68: DLR - Germen Aerospace Center | B68: DE | C68: Phase E Sentinel 1B | D68: 998,553.00
A69: DLR - Germen Aerospace Center | B69: DE | C69: Preparations and operations of the off-line Processing and Archiving Centres for sentinel gatellites | D69: 7,102,194.79
A70: DLR - German Aerospace Center | B70: DE | C70: Preparations and operations of the off-line Processing and Archiving Centres for sentinel isatellites | D70: 6,295,149.20
A71: DLR - German Aerospace Center | B71: DE | C71: 'SAR (Synthetic Aperture Radar) instruments on Sentinel satellites | D71: 98,763.00
A72: DLR - Germen Aerospace Center | B72: DE | C72: {Sentinel 1 Satellites C/D Units construction | D72: 1,269,933.00
A73: OMC INTERNATIONAL IMAGING LTD | B73: UK | C73: {Copernicus Space Component - Data Warehouse activities | D73: 38,796.00
A74: OTB/ SRO | B74: IT | C74: •Sentinel 1 Satellites C/D Units construction | D74: 383,760.00
... A190: ZARF/ TECHNIK AG | B190: DE | C190: Sentinel 2 Satellites C/D Units construction | D190: 406,635.00

Sheet 2016
A1: Name of Recipient | B1: Country | C1: Summary of Activities | D1: Contract value on Copernicus 2016
A2: ABSL SPACE PRODUCTS | B2: UK | C2: SENTINEL-6A/B-BATTERY | D2: 512,500.00
A3: ACRI-ST S.A.S. | B3: FR | C3: MISSION PERFORMANCE CENTERS (MPC) FOR SENTINELS. MPCs are responsible for calibration, validation, quality control and end-to-end system performance assessment. The MPCs include expert teams for specific cal/val, off-line quality control and algorithm correction activities. | D3: 2,000,000.00
A4: Advanced Computer Systems A.C.S. S.r.l. | B4: IT | C4: SENTINEL-3 GEOMETRIC CALIBRATION TOOL FOR IN ORBIT PERFORMANCES VERIFICATION | D4: 69,437.00
A5: AIM INFRAROT-MODULE GMBH | B5: DE | C5: SENTINEL-3 C/D UNITS - OME IR DETECTOR | D5: 70,000.00
A6: AIRBUS DEFENCE & SPACE NETHERLANDS | B6: NL | C6: SENTINEL-5 PHASE B2, C/D, E1. SD: ADS-NL. 1.00.3: DATA PROCESSING ENGINEERING. | D6: 1,095,731.00
A7: AIRBUS DEFENCE AND SPACE LIMITED | B7: UK | C7: SENTINEL-6A/B-MPPS | D7: 2,587,500.00
A8: AIRBUS DEFENCE AND SPACE SAS | B8: FR | C8: SENTINEL-2 C/D UNITS - MSI SYSTEM SUPPORT | D8: 331,250.00
A9: AIRBUS DEFENCE AND SPACE SAS | B9: FR | C9: SENTINEL-5 PHASE B2, C/D, E1. SD: ADS-F. 1.00.2: FOCAL PLANE SUBSYSTEM (FPS). | D9: 4,937,955.00
A10: AIRBUS DEFENCE AND SPACE SAS | B10: FR | C10: SENTINEL-6A/B-RMU | D10: 846,300.00
A11: AIRBUS DEFENCE AND SPACE, S.A.U | B11: ES | C11: SENTINEL-3 C/D UNITS - MWR | D11: 25,000.00
A12: AIRBUS DEFENCE AND SPACE, S.A.U | B12: ES | C12: SENTINEL-6A/B-HARNESS | D12: 950,008.00
... A116: ZARM TECHNIK AG | B116: DE | C116: SENTINEL-6A/B-MAG/MTQ | D116: 181,606.00

Sheet 2017
A1: Name of Recipient | B1: Country | C1: Summary of Activities | D1: Contract value on Copernicus 2017 (EUR)
A2: ACRI-ST S.A.S. | B2: FR | C2: SENTINEL-3 - PREPARATION AND OPERATIONS OF THE MISSION PERFORMANCE CENTRE (MPC) | D2: 559,007
A3: ACRI-ST S.A.S. | B3: FR | C3: Sentinel-3 OLCI In-flight Performance Analysis | D3: 262,284
A4: ACS ADVANCED COMPUTER SYSTEMS | B4: IT | C4: Sentinel-2 Payload Data Ground Segment (PDGS) system operations, maintenance and evolutions | D4: 1,144,723
A5: AIRBUS DEFENCE & SPACE NETHERLANDS(FORMER DUTCH SPACE) | B5: NL | C5: Sentinel 2 Satellites C/D Units construction | D5: 168,474
A6: AIRBUS DEFENCE AND SPACE LIMITED | B6: UK | C6: HOSTING, OPERATION, MAINTENANCE, EVOLUTION AND CONTENTMANAGEMENT OF AGENCYS COPERNICUS SENTINELS WORLD WIDEWEB SITES | D6: 500,000
A7: AIRBUS DEFENCE AND SPACE LIMITED | B7: UK | C7: SENTINEL-6A/B-MPPS | D7: 117,293
A8: AIRBUS DEFENCE AND SPACE SAS | B8: FR | C8: COPERNICUS DATA AND INFORMATION ACCESS SERVICES OPERATIONS | D8: 15,918,899
A9: AIRBUS DEFENCE AND SPACE, S.A.U | B9: ES | C9: SENTINEL-3 C/D UNITS - MWR | D9: 50,000
A10: AIRBUS DEFENCE AND SPACE, S.A.U | B10: ES | C10: SENTINEL-6A/B-HARNESS | D10: 17,108
A11: AIRBUS DS GEO SA | B11: FR | C11: COPERNICUS SPACE COMPONENT DATA ACCESS (CSC DA) DATA WAREHOUSE | D11: 7,000,000
A12: Airbus DS GmbH Sat | B12: DE | C12: Sentinel-1 Satellites C/D Units Construction | D12: 294,372
... A87: T-Systems International GmbH | B87: DE | C87: DATA CIRCULATION DISSEMINATION NETWORK AND SECURITY FOR SENTINELS | D87: 1,564,662

Sheet 2018
A1: Name of Recipient | B1: Country | C1: Summary of Activities | D1: Contract value
A2: ATOS CONVERGENCE CREATORS GMBH | B2: AT | C2: SENTINEL-5 EGSE ACTIVITY | D2: 234,445.00
A3: CSL - CENTRE SPATIAL DE LIÈGE | B3: BE | C3: Sentinel 2 Satellites C/D Units construction | D3: 1,379,013.00
A4: AIM INFRAROT-MODULE GMBH | B4: DE | C4: Sentinel-3 Satellites C/D Units construction | D4: 50,000.00
A5: Airbus DS GmbH Sat | B5: DE | C5: Sentinel 2 Satellites C/D Units construction | D5: 511,598.00
A6: Airbus DS GmbH Sat | B6: DE | C6: Sentinel-1 Satellites C/D Units Construction | D6: 2,132,915.00
A7: Airbus DS GmbH Sat | B7: DE | C7: SENTINEL-5 PHASE B2, C/D | D7: 3,233,686.00
A8: Airbus DS GmbH Sat | B8: DE | C8: Sentinel-6 A/B Satellite Instrument Construction | D8: 884,976.00
A9: EUROPEAN SPACE IMAGING GMBH | B9: DE | C9: COPERNICUS SPACE COMPONENT DATA ACCESS (CSC DA) | D9: 3,503,291.00
A10: AIRBUS DEFENCE AND SPACE, S.A.U | B10: ES | C10: EC/ESA COPERNICUS - | D10: 311,825.00
A11: AIRBUS DEFENCE AND SPACE, S.A.U | B11: ES | C11: Sentinel-3 Satellites C/D Units construction | D11: 18,592.00
A12: CRISA SA COMPUTADORAS REDES E INGENIERIA | B12: ES | C12: SENTINEL-5 SWIR SS ACTIVITY | D12: 18,444.00
... A82: VITO VL.INST.TECHN.ONDERZOEK | B82: BE | C82: COPERNICUS SPACE COMPONENT DATA ACCESS (CSC DA) DATA WAREHOUSE | D82: 939,276.00

Sheet 2019
A1: Name of Recipient | B1: Country | C1: Summary of Activities | D1: Contract value on Copernicus 2019 (€)
A2: ATOS IT SOLUTIONS & SERVICES GMBH | B2: AT | C2: SENTINEL-5 EGSE ACTIVITY | D2: 164,065.00
A3: ATOS IT SOLUTIONS & SERVICES GMBH | B3: AT | C3: SENTINEL-6 A/B - EGSE | D3: 53,428.00
A4: C-CORE | B4: CA | C4: SENTINEL-1 TRANSPONDER REFURBISHMENT | D4: 248,500.00
A5: ALMATECH SA | B5: CH | C5: SENTINEL-5 IOMSR ACTIVITY | D5: 1,222,225.00
A6: Airbus Def&Space GmbH | B6: DE | C6: Sentinel 2 Satellites C/D Units construction | D6: 2,103,804.00
A7: Airbus Def&Space GmbH | B7: DE | C7: Sentinel-1 Satellites C/D Units Construction | D7: 656,708.00
A8: Airbus Def&Space GmbH | B8: DE | C8: SENTINEL-5 PHASE B2 | D8: 3,109,000.00
A9: Airbus Def&Space GmbH | B9: DE | C9: SENTINEL-6 A/B - PRIME | D9: 1,119,222.00
A10: DLR - GERMAN AEROSPACE CENTER | B10: DE | C10: OFF-LINE PROCESSING AND ARCHIVING CENTRES (PACS) | D10: 2,494,747.99
A11: DLR - GERMAN AEROSPACE CENTER | B11: DE | C11: SENTINEL-1 AUXILIARY PRODUCT FOR PRECISE ATMOSPHERIC AND GEODETIC CORRECTION | D11: 599,906.00
A12: DLR - GERMAN AEROSPACE CENTER | B12: DE | C12: SENTINEL-5 PRECURSOR PAYLOAD DATA GROUND SEGMENT UPGRADE TO OPERATIONS | D12: 837,225.00
... A95: VITO VL.INST.TECHN.ONDERZOEK | B95: BE | C95: COPERNICUS SPACE COMPONENT DATA ACCESS (CSC DA) DATA WAREHOUSE | D95: 329,165.00

Sheet 2020
A1: Name of Recipient | B1: Country | C1: Summary of Activities | D1: Contract value on Copernicus 2020 (€)
A2: ACRI-ST S.A.S. | B2: FR | C2: LTA SERVICE FOR SENTINEL-1, 2, 3 OVER THE PERIOD 2020-2022 | D2: 1,483,400.00
A3: ACRI-ST S.A.S. | B3: FR | C3: PREPARATION AND OPERATIONS OF THE MISSION PERFORMANCE CENTRE (MPC) FOR THE GMES SENTINEL-3 MISSION | D3: 495,042.00
A4: ACRI-ST S.A.S. | B4: FR | C4: COPERNICUS SPACE COMPONENT VALIDATION FOR LAND SURFACE TEMPERATURE, AEROSOL OPTICAL DEPTH AND WATER VAPOUR SENTINEL-3 PRODUCTS | D4: 713,760.00
A5: ACRI-ST S.A.S. | B5: FR | C5: CORE PRODUCTS ALGORITHM STUDIES | D5: 260,898.00
A6: Advanced Computer Systems A.C.S. S.r.l. | B6: IT | C6: SENTINEL-2 PAYLOAD DATA GROUND SEGMENT SYSTEM OPERATIONS, MAINTENANCE AND EVOLUTION | D6: 155,463.00
A7: ADWÄISEO | B7: LU | C7: LTA SERVICE FOR SENTINEL-1, 2, 3 OVER THE PERIOD 2020-2022 | D7: 596,600.00
A8: Airbus Def&Space GmbH | B8: DE | C8: Sentinel 2 Satellites C/D Units construction | D8: 1,309,720.00
A9: Airbus Def&Space GmbH | B9: DE | C9: SENTINEL-5 - PRIME | D9: 1,095,731.00
A10: Airbus Def&Space GmbH | B10: DE | C10: SENTINEL-6 A/B - PRIME | D10: 1,187,827.00
A11: AIRBUS DEFENCE & SPACE NETHERLANDS B.V. | B11: NL | C11: Sentinel 2 Satellites C/D Units construction | D11: 21,250.00
A12: Airbus Defence and Space GmbH | B12: DE | C12: COPERNICUS DIGITAL ELEVATION MODEL (DEM) | D12: 12,000,000.00
... A155: WERUM SOFTWARE & SYSTEMS AG | B155: BE | C155: LONG TERM ARCHIVE SERVICE | D155: 1,880,000.00

Sheet 2021
A1: Name of Recipient | B1: Country | C1: Summary of Activities | D1: Contract value on Copernicus 2021 (€)
A2: ACRI-ST S.A.S. | B2: FR | C2: COPERNICUS SPACE COMPONENT SENTINEL OPTICAL IMAGING MISSION PERFORMANCE CLUSTER SERVICE | D2: 3,609,997.00
A3: ACRI-ST S.A.S. | B3: FR | C3: ESA GROUND SEGMENT OPERATIONS FRAMEWORK PRODUCTION SERVICE | D3: 6,264,990.00
A4: ACRI-ST S.A.S. | B4: FR | C4: PREPARATION AND OPERATIONS OF THE MISSION PERFORMANCE CENTRE (MPC) FOR SENTINEL-2 MISSION | D4: 208,998.00
A5: ACRI-ST S.A.S. | B5: FR | C5: S-3 L1 IPF MAINTENANCE | D5: 336,398.00
A6: Advanced Computer Systems A.C.S. S.r.l. | B6: IT | C6: SENTINEL-1 PAYLOAD DATA GROUND SEGMENT SYSTEM OPERATIONS, MAINTENANCE AND EVOLUTIONS | D6: 108,380.00
A7: Advanced Computer Systems A.C.S. S.r.l. | B7: IT | C7: SENTINEL-2 PAYLOAD DATA GROUND SEGMENT SYSTEM OPERATIONS, MAINTENANCE AND EVOLUTION | D7: 199,104.00
A8: Airbus Def&Space GmbH | B8: DE | C8: Sentinel 2 Satellites C/D Units construction | D8: 25,563,317.00
A9: Airbus Def&Space GmbH | B9: DE | C9: Sentinel-1 Satellites C/D Units Construction | D9: 4,921,616.00
A10: Airbus Def&Space GmbH | B10: DE | C10: Sentinel-6 Satellites A/B Units construction | D10: 9,929,745.00
A11: AIRBUS DEFENCE & SPACE NETHERLANDS B.V. | B11: NL | C11: Sentinel 2 Satellites C/D Units construction | D11: 63,327.00
A12: AIRBUS DEFENCE & SPACE NETHERLANDS B.V. | B12: NL | C12: Sentinel-1 Satellites C/D Units Construction | D12: 454,133.00
... A224: TELESPAZIO S.P.A. | B224: IT | C224: PRISM: COPERNICUS CONTRIBUTING MISSIONS ACCESS SUPPORT FUNCTIONS AND PLATFORM | D224: 3,492,063.00

Sheet 2022
A1: Name of Recipient | B1: Country | C1: Summary of Activities | D1: Contract value on Copernicus 2022 (€)
A2: ABSOLUT-SYSTEM | B2: FR | C2: Development of CO2M Spacecraft | D2: 106,272.00
A3: ABSOLUT-SYSTEM | B3: FR | C3: Development of LSTM Spacecraft | D3: 117,527.00
A4: ACRI-ST S.A.S. | B4: FR | C4: Development of CHIME Spacecraft | D4: 220,757.00
A5: ACRI-ST S.A.S. | B5: FR | C5: Development of CO2M Spacecraft | D5: 1,153,954.00
A6: ACRI-ST S.A.S. | B6: FR | C6: COPERNICUS LTA SERVICE FOR SENTINEL-1, 2, 3 | D6: 1,639,667.00
A7: ACRI-ST S.A.S. | B7: FR | C7: COPERNICUS SPACE COMPONENTS - COMPETITIVE FRAME CONTRACTS - ESA GROUND SEGMENT OPERATIONS FRAMEWORK PRODUCTION SERVICE | D7: 3,749,508.00
A8: ACRI-ST S.A.S. | B8: FR | C8: COPERNICUS SPACE COMPONENT SENTINEL OPTICAL IMAGING MISSION PERFORMANCE CLUSTER SERVICE | D8: 28,993,513.00
A9: ACTIVE SPACE TECHNOLOGIES SA | B9: PT | C9: Development of CIMR Spacecraft | D9: 1,426,002.00
A10: ACTIVE SPACE TECHNOLOGIES SA | B10: PT | C10: Development of LSTM Spacecraft | D10: 214,960.00
A11: ADMATIS LTD | B11: HU | C11: Development of CHIME Spacecraft | D11: 301,551.00
A12: ADMATIS LTD | B12: HU | C12: Development of CO2M Spacecraft | D12: 184,421.00
... A334: ZARM TECHNIK A G | B334: DE | C334: Development of ROSE-L Spacecraft | D334: 333,850.00
